{
  "generatedAt": "2026-06-22T17:43:03.394Z",
  "cachedAt": "2026-06-22T17:43:03.394Z",
  "cacheVersion": "20260622-deck-instance-labels",
  "cacheKey": "36e9cb63da37254357f9",
  "cache": "refresh",
  "stale": false,
  "descriptor": {
    "type": "card",
    "cardId": 76263644,
    "cardName": "Destiny End Dragoon",
    "cardArchetype": "Destiny HERO",
    "format": "md",
    "limit": 48
  },
  "samples": [
    {
      "id": 580388,
      "title": "YAGO",
      "url": "https://ygoprodeck.com/deck/yago-580388-580388",
      "source": "YGOPRODeck Public Deck",
      "format": "md",
      "creator": "sjnobiles",
      "tournament": "Master Duel Decks",
      "placement": "",
      "date": "3 weeks ago",
      "views": 931,
      "rating": 0,
      "archetypes": [],
      "mainIds": [
        83965310,
        74841885,
        40044918,
        83986578,
        29654737,
        42009836,
        19740112,
        423585,
        423585,
        423585,
        36745317,
        9350312,
        9350312,
        9350312,
        16605586,
        62133026,
        5519829,
        81519836,
        81519836,
        17272964,
        71650854,
        71650854,
        71650854,
        52947044,
        69162969,
        69162969,
        12580477,
        7477101,
        7477101,
        7477101,
        89558743,
        89558743,
        89558743,
        25311006,
        25311006,
        35269904,
        35269904,
        15693423,
        15693423,
        15693423
      ],
      "extraIds": [
        76263644,
        60461804,
        40509732,
        25862681,
        33198837,
        90448279,
        93039339,
        2061963,
        32530043,
        2857636,
        19324993,
        7480763,
        7480763,
        13117073,
        70369116
      ],
      "sideIds": [
        29439831,
        29439831,
        29439831,
        61822419,
        81756619,
        81756619,
        81756619,
        19403423
      ],
      "metaText": "Vernusylph",
      "sourceRank": 2,
      "ageDays": 21
    },
    {
      "id": 533087,
      "title": "Timelord Morganite",
      "url": "https://ygoprodeck.com/deck/timelord-morganite-533087-533087",
      "source": "YGOPRODeck Public Deck",
      "format": "md",
      "creator": "sjnobiles",
      "tournament": "Master Duel Decks",
      "placement": "",
      "date": "1 month ago",
      "views": 3397,
      "rating": 0,
      "archetypes": [],
      "mainIds": [
        91712985,
        91712985,
        91712985,
        83965310,
        74841885,
        74841885,
        83986578,
        29439831,
        29439831,
        29439831,
        42009836,
        19740112,
        423585,
        423585,
        423585,
        15079028,
        15079028,
        15079028,
        16605586,
        5519829,
        71650854,
        71650854,
        71650854,
        52947044,
        61822419,
        69162969,
        69162969,
        33907039,
        33907039,
        33907039,
        12580477,
        81756619,
        81756619,
        81756619,
        19403423,
        35269904,
        35269904,
        10045474,
        10045474,
        10045474
      ],
      "extraIds": [
        76263644,
        60461804,
        40509732,
        25862681,
        90448279,
        93039339,
        46871387,
        32530043,
        49202162,
        2857636,
        19324993,
        29301450,
        7480763,
        65741786,
        70369116
      ],
      "sideIds": [],
      "metaText": "Timelord",
      "sourceRank": 2,
      "ageDays": 30
    },
    {
      "id": 702606,
      "title": "Game 8 HERO deck",
      "url": "https://ygoprodeck.com/deck/game-8-hero-deck-702606-702606",
      "source": "YGOPRODeck Public Deck",
      "format": "md",
      "creator": "Light Magician",
      "tournament": "Master Duel Decks",
      "placement": "",
      "date": "2 months ago",
      "views": 325,
      "rating": 0,
      "archetypes": [],
      "mainIds": [
        89943723,
        22091647,
        83965310,
        14124483,
        81866673,
        9411399,
        9411399,
        9411399,
        18094166,
        18094166,
        18094166,
        13650422,
        40044918,
        40044918,
        40044918,
        63362460,
        59392529,
        45195443,
        50720316,
        50720316,
        27780618,
        27780618,
        16605586,
        22865492,
        14558127,
        14558127,
        14558127,
        26964762,
        8949584,
        8949584,
        8949584,
        12071500,
        52947044,
        16169772,
        45906428,
        24094653,
        32807846,
        24224830,
        65681983,
        24299458,
        24299458,
        24299458,
        21143940,
        21143940,
        75047173,
        10045474,
        10045474,
        10045474
      ],
      "extraIds": [
        32828466,
        56733747,
        86165817,
        59642500,
        29095552,
        60461804,
        40854197,
        46759931,
        93347961,
        22908820,
        89870349,
        19324993,
        58004362
      ],
      "sideIds": [
        27204311,
        27204311,
        55063751,
        76263644,
        30757127,
        213326,
        48130397,
        43898403,
        20899496
      ],
      "metaText": "Elemenal HERO",
      "sourceRank": 2,
      "ageDays": 60
    },
    {
      "id": 690055,
      "title": "Destiny hero star warrior deck master duel",
      "url": "https://ygoprodeck.com/deck/destiny-hero-star-warrior-deck-master-duel-690055-690055",
      "source": "YGOPRODeck Public Deck",
      "format": "md",
      "creator": "starwarrior",
      "tournament": "Master Duel Decks",
      "placement": "",
      "date": "4 months ago",
      "views": 649,
      "rating": 0,
      "archetypes": [],
      "mainIds": [
        37780349,
        37780349,
        37780349,
        9411399,
        9411399,
        9411399,
        83965310,
        17132130,
        64184058,
        91691605,
        63362460,
        27780618,
        27780618,
        40044918,
        45195443,
        45195443,
        30118701,
        30118701,
        60822251,
        60822251,
        52947044,
        52947044,
        52947044,
        213326,
        213326,
        213326,
        45809008,
        45809008,
        45809008,
        24094653,
        24094653,
        8949584,
        32807846,
        83764719,
        25311006,
        24224830,
        21143940,
        48032131,
        48032131,
        48032131
      ],
      "extraIds": [
        60461804,
        90579153,
        93657021,
        30757127,
        69394324,
        76263644,
        32615065,
        32615065,
        96220350,
        96220350,
        96220350,
        99991455,
        49161188,
        58481572,
        98642179
      ],
      "sideIds": [],
      "metaText": "just testing",
      "sourceRank": 2,
      "ageDays": 120
    },
    {
      "id": 626745,
      "title": "Destiny hero deck master duel pure",
      "url": "https://ygoprodeck.com/deck/destiny-hero-deck-master-duel-pure-626745-626745",
      "source": "YGOPRODeck Public Deck",
      "format": "md",
      "creator": "lightness4000",
      "tournament": "Master Duel Decks",
      "placement": "",
      "date": "10 months ago",
      "views": 1335,
      "rating": 0,
      "archetypes": [],
      "mainIds": [
        91691605,
        91691605,
        91691605,
        63362460,
        63362460,
        63362460,
        64184058,
        16605586,
        66262416,
        56570271,
        37780349,
        37780349,
        9411399,
        9411399,
        9411399,
        17132130,
        17132130,
        83965310,
        83965310,
        45809008,
        45809008,
        45809008,
        52947044,
        52947044,
        52947044,
        32671443,
        32671443,
        6186304,
        8698851,
        8698851,
        8698851,
        26841274,
        26841274,
        26841274,
        4008212,
        4008212,
        4008212,
        48032131,
        48032131,
        48032131
      ],
      "extraIds": [
        30757127,
        60461804,
        60461804,
        60461804,
        90579153,
        90579153,
        69394324,
        93657021,
        45170821,
        45170821,
        46759931,
        46759931,
        76263644,
        76263644,
        76263644
      ],
      "sideIds": [],
      "metaText": "pure",
      "sourceRank": 2,
      "ageDays": 300
    },
    {
      "id": 336989,
      "title": "Destiny Hero",
      "url": "https://ygoprodeck.com/deck/destiny-hero-336989-336989",
      "source": "YGOPRODeck Public Deck",
      "format": "md",
      "creator": "Chiko Asad",
      "tournament": "Master Duel Decks",
      "placement": "",
      "date": "2 years ago",
      "views": 2315,
      "rating": 0,
      "archetypes": [],
      "mainIds": [
        56570271,
        66262416,
        23434538,
        23434538,
        22865492,
        22865492,
        14558127,
        14558127,
        14558127,
        16605586,
        40044918,
        27780618,
        27780618,
        50720316,
        91691605,
        91691605,
        91691605,
        64184058,
        48150362,
        18094166,
        18094166,
        18094166,
        37780349,
        9411399,
        9411399,
        17132130,
        83965310,
        24094653,
        32807846,
        45809008,
        45809008,
        8949584,
        8949584,
        8949584,
        52947044,
        52947044,
        6186304,
        6186304,
        21143940,
        21143940
      ],
      "extraIds": [
        58481572,
        30757127,
        45170821,
        46759931,
        59642500,
        90579153,
        60461804,
        76263644,
        93657021,
        69394324,
        1948619,
        58004362,
        58004362,
        70369116,
        63813056
      ],
      "sideIds": [],
      "metaText": "destiny hero deck",
      "sourceRank": 2,
      "ageDays": 730
    },
    {
      "id": 346969,
      "title": "Destiny HERO - Master Duel - DARK vs. LIGHT",
      "url": "https://ygoprodeck.com/deck/destiny-hero-master-duel-dark-vs-light-346969-346969",
      "source": "YGOPRODeck Public Deck",
      "format": "md",
      "creator": "Master Duel Decks",
      "tournament": "Master Duel Decks",
      "placement": "",
      "date": "2 years ago",
      "views": 1511,
      "rating": 0,
      "archetypes": [],
      "mainIds": [
        26964762,
        64184058,
        16605586,
        16605586,
        16605586,
        13093792,
        56570271,
        17132130,
        48150362,
        66262416,
        91691605,
        91691605,
        37780349,
        37780349,
        37780349,
        9411399,
        9411399,
        83965310,
        50720316,
        50720316,
        27780618,
        8949584,
        18973184,
        24224830,
        45809008,
        45809008,
        45809008,
        32671443,
        32671443,
        81439173,
        52947044,
        21143940,
        21143940,
        24094653,
        24094653,
        12580477,
        32807846,
        48130397,
        4008212,
        48032131
      ],
      "extraIds": [
        76263644,
        30757127,
        60461804,
        60461804,
        69394324,
        93657021,
        90579153,
        90579153,
        58481572,
        58481572,
        58481572,
        70369116,
        41209827,
        46759931,
        58004362
      ],
      "sideIds": [],
      "metaText": "Master Duel Deck - Destiny HERO - DARK vs. LIGHT",
      "sourceRank": 2,
      "ageDays": 730
    },
    {
      "id": 336679,
      "title": "Converging Illusion of Destiny",
      "url": "https://ygoprodeck.com/deck/converging-illusion-of-destiny-336679-336679",
      "source": "YGOPRODeck Public Deck",
      "format": "md",
      "creator": "YGOPRODeck Bot",
      "tournament": "Master Duel Decks",
      "placement": "",
      "date": "2 years ago",
      "views": 1464,
      "rating": 0,
      "archetypes": [],
      "mainIds": [
        17132130,
        83965310,
        83965310,
        81866673,
        9411399,
        9411399,
        18094166,
        37780349,
        63362460,
        63362460,
        91691605,
        91691605,
        64184058,
        13093792,
        27780618,
        16605586,
        16605586,
        16605586,
        22865492,
        56570271,
        6186304,
        45809008,
        45809008,
        45809008,
        32671443,
        52947044,
        52947044,
        18144507,
        83764719,
        24094653,
        32807846,
        24224830,
        24224830,
        8267140,
        95286165,
        48130397,
        48130397,
        48032131,
        4008212,
        81223446
      ],
      "extraIds": [
        76263644,
        76263644,
        93657021,
        69394324,
        69394324,
        90579153,
        90579153,
        45170821,
        45170821,
        60461804,
        60461804,
        46759931,
        30757127,
        30757127,
        54757758
      ],
      "sideIds": [],
      "metaText": "Fusion Festival",
      "sourceRank": 2,
      "ageDays": 730
    },
    {
      "id": 346891,
      "title": "Destiny HERO - Master Duel - DARK vs. LIGHT",
      "url": "https://ygoprodeck.com/deck/destiny-hero-master-duel-dark-vs-light-346891-346891",
      "source": "YGOPRODeck Public Deck",
      "format": "md",
      "creator": "Master Duel Decks",
      "tournament": "Master Duel Decks",
      "placement": "",
      "date": "2 years ago",
      "views": 1019,
      "rating": 0,
      "archetypes": [],
      "mainIds": [
        81866673,
        81866673,
        64184058,
        64184058,
        16605586,
        56570271,
        17132130,
        17132130,
        40591390,
        40591390,
        91691605,
        37780349,
        37780349,
        9411399,
        9411399,
        83965310,
        83965310,
        50720316,
        50720316,
        50720316,
        18094166,
        18094166,
        18094166,
        22865492,
        27780618,
        27780618,
        8949584,
        8949584,
        8949584,
        24224830,
        24224830,
        45809008,
        45809008,
        45809008,
        52947044,
        21143940,
        21143940,
        21143940,
        24094653,
        24094653,
        32807846,
        38120068,
        38120068,
        38120068
      ],
      "extraIds": [
        76263644,
        30757127,
        60461804,
        60461804,
        69394324,
        90579153,
        90579153,
        59642500,
        58481572,
        58481572,
        45170821,
        46759931,
        58004362,
        58004362,
        63813056
      ],
      "sideIds": [],
      "metaText": "Master Duel Deck - Destiny HERO - DARK vs. LIGHT",
      "sourceRank": 2,
      "ageDays": 730
    },
    {
      "id": 343630,
      "title": "Destiny HERO - Master Duel - Ranked Duels (Season 20)",
      "url": "https://ygoprodeck.com/deck/destiny-hero-master-duel-ranked-duels-season-20-343630-343630",
      "source": "YGOPRODeck Public Deck",
      "format": "md",
      "creator": "Master Duel Decks",
      "tournament": "Master Duel Decks",
      "placement": "",
      "date": "2 years ago",
      "views": 891,
      "rating": 0,
      "archetypes": [],
      "mainIds": [
        64184058,
        16605586,
        13093792,
        56570271,
        17132130,
        36625827,
        40591390,
        66262416,
        91691605,
        91691605,
        91691605,
        37780349,
        9411399,
        9411399,
        83965310,
        63060238,
        63060238,
        50720316,
        45195443,
        45195443,
        8949584,
        8949584,
        75041269,
        6186304,
        53527835,
        45809008,
        45809008,
        45809008,
        32671443,
        52947044,
        52947044,
        21143940,
        21143940,
        21143940,
        24094653,
        24094653,
        24094653,
        32807846,
        4008212,
        35464895
      ],
      "extraIds": [
        23204029,
        76263644,
        30757127,
        60461804,
        69394324,
        93657021,
        90579153,
        59642500,
        58481572,
        62624486,
        46759931,
        58004362,
        58004362,
        63813056,
        1948619
      ],
      "sideIds": [],
      "metaText": "Master Duel Deck - Destiny HERO - Ranked Duels (Season 20)",
      "sourceRank": 2,
      "ageDays": 730
    },
    {
      "id": 348270,
      "title": "Elemental HERO - Master Duel - Ranked Duels (Season 20)",
      "url": "https://ygoprodeck.com/deck/elemental-hero-master-duel-ranked-duels-season-20-348270-348270",
      "source": "YGOPRODeck Public Deck",
      "format": "md",
      "creator": "Master Duel Decks",
      "tournament": "Master Duel Decks",
      "placement": "",
      "date": "2 years ago",
      "views": 764,
      "rating": 0,
      "archetypes": [],
      "mainIds": [
        21844576,
        58932615,
        89943723,
        89943723,
        14558127,
        14558127,
        40740224,
        40740224,
        65192027,
        16605586,
        17132130,
        9411399,
        83965310,
        63060238,
        59392529,
        50720316,
        50720316,
        13256226,
        13256226,
        40044918,
        40044918,
        13650422,
        17955766,
        79856792,
        18094166,
        22865492,
        27780618,
        27780618,
        8949584,
        24224830,
        6186304,
        12071500,
        213326,
        213326,
        80170678,
        10186633,
        24299458,
        52947044,
        74335036,
        18144507,
        16169772,
        16169772,
        14532163,
        14532163,
        21143940,
        21143940,
        35255456,
        45906428,
        83764719,
        14088859,
        24094653,
        64014615,
        12580477,
        12580477,
        32807846,
        48032131,
        75047173,
        10045474,
        23002292,
        41420027
      ],
      "extraIds": [
        31817415,
        76263644,
        60461804,
        40854197,
        64655485,
        90050480,
        35809262,
        56733747,
        22908820,
        86165817,
        29095552,
        58481572,
        86346643,
        58004362,
        19324993
      ],
      "sideIds": [],
      "metaText": "Master Duel Deck - Elemental HERO - Ranked Duels (Season 20)",
      "sourceRank": 2,
      "ageDays": 730
    },
    {
      "id": 448014,
      "title": "Heroes Rising Redux",
      "url": "https://ygoprodeck.com/deck/heroes-rising-redux-448014-448014",
      "source": "YGOPRODeck Public Deck",
      "format": "md",
      "creator": "BuraiEX",
      "tournament": "Master Duel Decks",
      "placement": "",
      "date": "2 years ago",
      "views": 729,
      "rating": 0,
      "archetypes": [],
      "mainIds": [
        89943723,
        89943723,
        5126490,
        78371393,
        17132130,
        82697428,
        83965310,
        58554959,
        14124483,
        13256226,
        13256226,
        81866673,
        45659520,
        18094166,
        13650422,
        40044918,
        64184058,
        95943058,
        59392529,
        59392529,
        45195443,
        63060238,
        63060238,
        50720316,
        27780618,
        54185227,
        16605586,
        43237273,
        80344569,
        11881272,
        72043279,
        8949584,
        12071500,
        6498706,
        52947044,
        18144507,
        16169772,
        45906428,
        83764719,
        14088859,
        24094653,
        12580477,
        32807846,
        21143940,
        21143940,
        5318639,
        48130397,
        48130397,
        48032131,
        51452091,
        41420027,
        91392974,
        8698851,
        75047173,
        31548215,
        10045474,
        5650082,
        1005587
      ],
      "extraIds": [
        76263644,
        40080312,
        90307498,
        86676862,
        86165817,
        3642509,
        45170821,
        1945387,
        29095552,
        60461804,
        33574806,
        93347961,
        64655485,
        22908820,
        58481572
      ],
      "sideIds": [],
      "metaText": "First/Main Deck",
      "sourceRank": 2,
      "ageDays": 730
    },
    {
      "id": 445801,
      "title": "Pre-destiny timely heroes of the hours",
      "url": "https://ygoprodeck.com/deck/pre-destiny-timely-heroes-of-the-hours-445801-445801",
      "source": "YGOPRODeck Public Deck",
      "format": "md",
      "creator": "DeCard_KingShark",
      "tournament": "Master Duel Decks",
      "placement": "",
      "date": "2 years ago",
      "views": 599,
      "rating": 0,
      "archetypes": [],
      "mainIds": [
        17132130,
        17132130,
        17132130,
        83965310,
        83965310,
        83965310,
        81866673,
        81866673,
        28355718,
        37780349,
        91691605,
        91691605,
        64184058,
        64184058,
        13093792,
        13093792,
        13093792,
        93431862,
        93431862,
        80744121,
        6186304,
        74329404,
        22147147,
        11881272,
        75041269,
        89899996,
        45809008,
        45809008,
        52947044,
        52947044,
        25614410,
        72204747,
        24094653,
        24224830,
        24299458,
        52340444,
        98338152,
        48130397,
        48130397,
        48130397,
        48032131,
        48032131,
        78783370,
        65703851,
        9070454,
        4440873,
        85854214,
        85854214,
        85854214,
        38891741,
        34507039,
        43405287,
        8698851,
        9201964,
        62868900,
        26841274,
        26841274,
        26841274,
        15294090,
        35464895
      ],
      "extraIds": [
        76263644,
        76263644,
        76263644,
        93657021,
        93657021,
        93657021,
        69394324,
        69394324,
        69394324,
        90579153,
        90579153,
        60461804,
        60461804,
        30757127,
        30757127
      ],
      "sideIds": [
        40591390,
        9411399,
        9411399,
        48150362,
        54749427,
        16605586,
        77608643,
        22147147,
        22147147,
        53527835,
        45809008,
        48032131,
        43405287,
        43405287,
        8698851
      ],
      "metaText": "Well at least give this deck some credit, it was a lot easier to build compared to my elemental hero one.",
      "sourceRank": 2,
      "ageDays": 730
    },
    {
      "id": 416351,
      "title": "Illusions of Dragoon",
      "url": "https://ygoprodeck.com/deck/illusions-of-dragoon-416351-416351",
      "source": "YGOPRODeck Public Deck",
      "format": "md",
      "creator": "Esparanta",
      "tournament": "Master Duel Decks",
      "placement": "",
      "date": "2 years ago",
      "views": 587,
      "rating": 0,
      "archetypes": [],
      "mainIds": [
        487395,
        487395,
        7902349,
        44519536,
        70903634,
        8124921,
        21615956,
        27125110,
        63941210,
        33537328,
        45836982,
        45221020,
        45221020,
        45221020,
        423585,
        423585,
        423585,
        14644902,
        67775894,
        67775894,
        67775894,
        71645242,
        1475311,
        1475311,
        1475311,
        38699854,
        93946239,
        93946239,
        93946239,
        85852291,
        85852291,
        85852291,
        73244186,
        67169062,
        67169062,
        67169062,
        23314220,
        70368879,
        70368879,
        70368879,
        18756904,
        18756904,
        18756904,
        9952083,
        64014615,
        22589918,
        22589918,
        22589918
      ],
      "extraIds": [
        76263644,
        87188910,
        30983281,
        25862681,
        64880894,
        90953320,
        12948099,
        12948099,
        46057733,
        25200959,
        81846453,
        50091196,
        50091196,
        66011101,
        74997493
      ],
      "sideIds": [
        17132130,
        83965310,
        69015963,
        24094653
      ],
      "metaText": "Dragoon FTK ft. Summoner+Linewalker",
      "sourceRank": 2,
      "ageDays": 730
    },
    {
      "id": 357149,
      "title": "Blue-Eyes - Master Duel - Ranked Duels (Season 21)",
      "url": "https://ygoprodeck.com/deck/blue-eyes-master-duel-ranked-duels-season-21-357149-357149",
      "source": "YGOPRODeck Public Deck",
      "format": "md",
      "creator": "Master Duel Decks",
      "tournament": "Master Duel Decks",
      "placement": "",
      "date": "2 years ago",
      "views": 360,
      "rating": 0,
      "archetypes": [],
      "mainIds": [
        97127906,
        89631139,
        89631139,
        89631139,
        29904964,
        38517737,
        15146890,
        80280944,
        75064463,
        61692648,
        88241506,
        88241506,
        88241506,
        43268675,
        43268675,
        40318957,
        31553716,
        53129443,
        66788016,
        74137509,
        16762927,
        14532163,
        82432018,
        56948373,
        22046459,
        83764719,
        5318639,
        24094653,
        67169062,
        49238328,
        49238328,
        12580477,
        33904024,
        30683373,
        97169186,
        60764581,
        72302403,
        911883,
        911883,
        78574395,
        62325062,
        29401950,
        97077563,
        43250041,
        47475363,
        60082869,
        96355986,
        61705417,
        62279055,
        44095762,
        73729209,
        126218,
        53582587,
        4206964,
        12607053
      ],
      "extraIds": [
        2129638,
        2129638,
        2129638,
        23995346,
        23995346,
        23995346,
        581014,
        41721210,
        76263644,
        42166000,
        69069911,
        56532353,
        84013237,
        62541668,
        55285840
      ],
      "sideIds": [],
      "metaText": "Master Duel Deck - Blue-Eyes - Ranked Duels (Season 21)",
      "sourceRank": 2,
      "ageDays": 730
    },
    {
      "id": 307859,
      "title": "Master duel fun deck",
      "url": "https://ygoprodeck.com/deck/master-duel-fun-deck-307859-307859",
      "source": "YGOPRODeck Public Deck",
      "format": "md",
      "creator": "muslim",
      "tournament": "Master Duel Decks",
      "placement": "",
      "date": "3 years ago",
      "views": 2921,
      "rating": 0,
      "archetypes": [],
      "mainIds": [
        17132130,
        55591586,
        55591586,
        83965310,
        81866673,
        9411399,
        9411399,
        70095154,
        70095154,
        70095154,
        31786629,
        31786629,
        31786629,
        59281922,
        59281922,
        29975188,
        29975188,
        29975188,
        5370235,
        5370235,
        77625948,
        77625948,
        41230939,
        41230939,
        3019642,
        3019642,
        67159705,
        67159705,
        45078193,
        82562802,
        14558127,
        14558127,
        23434538,
        23434538,
        23893227,
        23893227,
        23893227,
        1142880,
        1142880,
        56364287,
        56364287,
        64753988,
        60600126,
        60600126,
        60600126,
        86686671,
        86686671,
        33041277,
        63031396,
        63031396,
        52875873,
        52947044,
        63995093,
        63995093,
        83764719,
        95238394,
        95238394,
        1157683,
        82428674,
        18597560
      ],
      "extraIds": [
        37542782,
        1546123,
        41685633,
        76263644,
        82315403,
        18967507,
        15291624,
        60461804,
        90448279,
        10443957,
        58069384,
        66403530,
        67288539,
        46724542,
        70369116
      ],
      "sideIds": [],
      "metaText": "this is the deck I own in master duel",
      "sourceRank": 2,
      "ageDays": 1095
    },
    {
      "id": 307931,
      "title": "updated",
      "url": "https://ygoprodeck.com/deck/updated-307931-307931",
      "source": "YGOPRODeck Public Deck",
      "format": "md",
      "creator": "muslim",
      "tournament": "Master Duel Decks",
      "placement": "",
      "date": "3 years ago",
      "views": 2428,
      "rating": 0,
      "archetypes": [],
      "mainIds": [
        17132130,
        55591586,
        55591586,
        83965310,
        81866673,
        9411399,
        9411399,
        70095154,
        70095154,
        70095154,
        31786629,
        31786629,
        31786629,
        59281922,
        59281922,
        29975188,
        29975188,
        29975188,
        5370235,
        5370235,
        77625948,
        77625948,
        41230939,
        41230939,
        3019642,
        3019642,
        67159705,
        67159705,
        45078193,
        82562802,
        14558127,
        14558127,
        23434538,
        23434538,
        23893227,
        23893227,
        1142880,
        1142880,
        56364287,
        56364287,
        64753988,
        44362883,
        60600126,
        60600126,
        60600126,
        86686671,
        86686671,
        33041277,
        63031396,
        63031396,
        52875873,
        52947044,
        63995093,
        63995093,
        83764719,
        95238394,
        95238394,
        1157683,
        82428674,
        18597560
      ],
      "extraIds": [
        1546123,
        41685633,
        76263644,
        82315403,
        44146295,
        15291624,
        70534340,
        60461804,
        90448279,
        10443957,
        58069384,
        66403530,
        67288539,
        46724542,
        70369116
      ],
      "sideIds": [],
      "metaText": "updated version",
      "sourceRank": 2,
      "ageDays": 1095
    },
    {
      "id": 328488,
      "title": "Terrible Hero's",
      "url": "https://ygoprodeck.com/deck/terrible-hero-s-328488-328488",
      "source": "YGOPRODeck Public Deck",
      "format": "md",
      "creator": "TheeSleepyPanda",
      "tournament": "Master Duel Decks",
      "placement": "",
      "date": "3 years ago",
      "views": 2016,
      "rating": 0,
      "archetypes": [],
      "mainIds": [
        89943723,
        89943723,
        27204311,
        27204311,
        79856792,
        5126490,
        78371393,
        17132130,
        83965310,
        13256226,
        13256226,
        13256226,
        81866673,
        9411399,
        9411399,
        18094166,
        13650422,
        13650422,
        40044918,
        91691605,
        59392529,
        59392529,
        45195443,
        45195443,
        50720316,
        50720316,
        27780618,
        16605586,
        22865492,
        14558127,
        14558127,
        23434538,
        23434538,
        23434538,
        40740224,
        40740224,
        56570271,
        12071500,
        45809008,
        45809008,
        45809008,
        213326,
        213326,
        52947044,
        52947044,
        18144507,
        14532163,
        14532163,
        45906428,
        45906428,
        83764719,
        14088859,
        14088859,
        24094653,
        24094653,
        24094653,
        32807846,
        21143940,
        21143940,
        21143940
      ],
      "extraIds": [
        86346643,
        76263644,
        69394324,
        90307498,
        86165817,
        22093873,
        60461804,
        40854197,
        46759931,
        22908820,
        58481572,
        1948619,
        19324993,
        58004362,
        70369116
      ],
      "sideIds": [],
      "metaText": "Terrible Fusion's",
      "sourceRank": 2,
      "ageDays": 1095
    },
    {
      "id": 242166,
      "title": "Diamond Dude Turbo Deck 2022",
      "url": "https://ygoprodeck.com/deck/diamond-dude-turbo-deck-2022-242166-242166",
      "source": "YGOPRODeck Public Deck",
      "format": "md",
      "creator": "Jollie Scarcrows",
      "tournament": "Master Duel Decks",
      "placement": "",
      "date": "4 years ago",
      "views": 5749,
      "rating": 0,
      "archetypes": [],
      "mainIds": [
        17132130,
        83965310,
        40591390,
        9411399,
        9411399,
        91691605,
        91691605,
        91691605,
        13093792,
        13093792,
        13093792,
        56570271,
        26964762,
        1475311,
        1475311,
        1475311,
        14532163,
        14532163,
        14532163,
        25311006,
        25311006,
        25311006,
        32807846,
        35261759,
        35261759,
        35261759,
        45809008,
        45809008,
        45809008,
        51549976,
        52947044,
        52947044,
        52947044,
        57734012,
        57734012,
        57734012,
        72204747,
        72204747,
        72204747,
        73680966,
        73680966,
        83764718,
        99674361
      ],
      "extraIds": [
        76263644,
        69394324,
        69394324,
        90579153,
        21140872,
        30757127,
        68396121,
        88177324,
        4280258,
        1948619,
        58004362,
        58004362,
        58004362,
        70369116
      ],
      "sideIds": [
        74677423,
        27204311,
        27204311,
        27204311,
        26964762,
        26964762,
        5133471,
        5133471,
        5133471,
        18144507,
        51549976,
        51549976,
        30459350,
        30459350,
        30459350
      ],
      "metaText": "Diamond Dude Deck 2022",
      "sourceRank": 2,
      "ageDays": 1460
    },
    {
      "id": 286742,
      "title": "Diamond Heroes",
      "url": "https://ygoprodeck.com/deck/diamond-heroes-286742-286742",
      "source": "YGOPRODeck Public Deck",
      "format": "md",
      "creator": "UnbornHexa",
      "tournament": "Master Duel Decks",
      "placement": "",
      "date": "4 years ago",
      "views": 1953,
      "rating": 0,
      "archetypes": [],
      "mainIds": [
        23434538,
        23434538,
        23434538,
        22865492,
        14558127,
        14558127,
        14558127,
        16605586,
        40044918,
        40044918,
        27780618,
        27780618,
        50720316,
        50720316,
        59392529,
        18094166,
        18094166,
        9411399,
        9411399,
        14124483,
        17132130,
        83965310,
        27204311,
        24094653,
        32807846,
        45906428,
        213326,
        8949584,
        52947044,
        52947044,
        5318639,
        5318639,
        48130397,
        48130397,
        21143940,
        21143940,
        21143940,
        24224830,
        10045474,
        41420027
      ],
      "extraIds": [
        58481572,
        89870349,
        22908820,
        40854197,
        3642509,
        46759931,
        29095552,
        22093873,
        59642500,
        41209827,
        60461804,
        76263644,
        58004362,
        70369116,
        63813056
      ],
      "sideIds": [],
      "metaText": "A Deck recipe for Master Duel to get on Diamond with Heroes. This was submitted for the Novakin Membership Tournament.",
      "sourceRank": 2,
      "ageDays": 1460
    }
  ]
}