{
  "generatedAt": "2026-06-22T17:29:21.263Z",
  "cachedAt": "2026-06-22T17:29:21.263Z",
  "cacheVersion": "20260622-deck-instance-labels",
  "cacheKey": "7a3099dfcd0d075cb92c",
  "cache": "refresh",
  "stale": false,
  "descriptor": {
    "type": "card",
    "cardId": 78397661,
    "cardName": "Ecclesia and the Dark Dragon",
    "cardArchetype": "Ecclesia",
    "format": "md",
    "limit": 48
  },
  "samples": [
    {
      "id": "md-meta:/rating-duels/june-2026/lunalight/slappmygoose/GMGe0/",
      "title": "Lunalight",
      "url": "https://www.masterduelmeta.com/rating-duels/june-2026/lunalight/slappmygoose/GMGe0/",
      "source": "Master Duel Meta Top Decks",
      "format": "md",
      "creator": "slappmygoose",
      "tournament": "Rating Duels",
      "placement": "",
      "date": "2026-06-22T07:36:05.181Z",
      "views": 1606.49,
      "rating": 3,
      "engines": [
        "The Fallen & The Virtuous"
      ],
      "notes": "",
      "archetypes": [
        "Lunalight",
        "The Fallen & The Virtuous"
      ],
      "mainIds": [
        23434538,
        11317977,
        11317977,
        11317977,
        83190280,
        35763582,
        35763582,
        35618217,
        35618217,
        14152693,
        50546208,
        87209160,
        87209160,
        42141493,
        42141493,
        42141493,
        8379983,
        8379983,
        8379983,
        47705572,
        58570206,
        58570206,
        58570206,
        24094653,
        48444114,
        48444114,
        87931906,
        81439173,
        2344618,
        2344618,
        57103969,
        57103969,
        24299458,
        24299458,
        24299458,
        99599062,
        99599062,
        30271097,
        30271097,
        30271097
      ],
      "extraIds": [
        81196066,
        81196066,
        97165977,
        87746184,
        11321089,
        24550676,
        24550676,
        54701958,
        54701958,
        78397661,
        96381979,
        85115440,
        48905153,
        66011101,
        29301450
      ],
      "sideIds": [],
      "metaText": "Master Duel Meta Top Decks Rating Duels Lunalight The Fallen & The Virtuous",
      "sourceRank": 0,
      "ageDays": 0
    },
    {
      "id": "md-meta:/rating-duels/june-2026/radiant-typhoon-zoodiac/ceo-of-copium/Bdeyh/",
      "title": "Radiant Typhoon Zoodiac",
      "url": "https://www.masterduelmeta.com/rating-duels/june-2026/radiant-typhoon-zoodiac/ceo-of-copium/Bdeyh/",
      "source": "Master Duel Meta Top Decks",
      "format": "md",
      "creator": "CEO Of Copium",
      "tournament": "Rating Duels",
      "placement": "",
      "date": "2026-06-22T07:44:07.853Z",
      "views": 1578.55,
      "rating": 3,
      "engines": [
        "Radiant Typhoon Vision",
        "Shiina",
        "The Fallen & The Virtuous"
      ],
      "notes": "",
      "archetypes": [
        "Radiant Typhoon Zoodiac",
        "Radiant Typhoon Vision",
        "Shiina",
        "The Fallen & The Virtuous"
      ],
      "mainIds": [
        94145021,
        94145021,
        23434538,
        14558127,
        14558127,
        14558127,
        54143349,
        54143349,
        54143349,
        27755794,
        80538047,
        80538047,
        80538047,
        78872731,
        78872731,
        78872731,
        16922142,
        16922142,
        16922142,
        85315450,
        53927851,
        12197223,
        5318639,
        5318639,
        5318639,
        24224830,
        24299458,
        24299458,
        24299458,
        25940932,
        67115133,
        67115133,
        67115133,
        20508881,
        20508881,
        20508881,
        30271097,
        30271097,
        30271097,
        53813120
      ],
      "extraIds": [
        87746184,
        78397661,
        65305468,
        26973555,
        4423206,
        74393852,
        85115440,
        48905153,
        11510448,
        41375811,
        90448279,
        29301450,
        39341885,
        39341885,
        49105782
      ],
      "sideIds": [],
      "metaText": "Master Duel Meta Top Decks Rating Duels Radiant Typhoon Zoodiac Radiant Typhoon Vision Shiina The Fallen & The Virtuous",
      "sourceRank": 0,
      "ageDays": 0
    },
    {
      "id": "md-meta:/rating-duels/june-2026/branded/sir🅱ichard/ZJEfS/",
      "title": "Branded",
      "url": "https://www.masterduelmeta.com/rating-duels/june-2026/branded/sir🅱ichard/ZJEfS/",
      "source": "Master Duel Meta Top Decks",
      "format": "md",
      "creator": "Sir🅱ichard",
      "tournament": "Rating Duels",
      "placement": "",
      "date": "2026-06-22T07:36:22.600Z",
      "views": 1525.21,
      "rating": 16,
      "engines": [
        "Dragoon",
        "Dark Magician of Destruction",
        "DMG Shining Sarc",
        "Radiant Typhoon Vision"
      ],
      "notes": "",
      "archetypes": [
        "Branded",
        "Dragoon",
        "Dark Magician of Destruction",
        "DMG Shining Sarc",
        "Radiant Typhoon Vision"
      ],
      "mainIds": [
        94145021,
        94145021,
        23434538,
        14558127,
        14558127,
        14558127,
        19304410,
        68468459,
        82489470,
        62962630,
        55273560,
        55273560,
        95515789,
        45883110,
        92110878,
        42141493,
        42141493,
        73819701,
        73819701,
        33854624,
        2501624,
        2501624,
        2501624,
        342673,
        2333466,
        79791878,
        79791878,
        48130397,
        48130397,
        24224830,
        23020408,
        22283204,
        22283204,
        24299458,
        24299458,
        29948294,
        29948294,
        29948294,
        78679226,
        78679226,
        20508881,
        20508881,
        30271097,
        30271097,
        30271097
      ],
      "extraIds": [
        66532962,
        59400890,
        37818794,
        41373230,
        87746184,
        87746184,
        85059922,
        44146295,
        24915933,
        51409648,
        76666602,
        76666602,
        59123194,
        78397661
      ],
      "sideIds": [],
      "metaText": "Master Duel Meta Top Decks Rating Duels Branded Dragoon Dark Magician of Destruction DMG Shining Sarc Radiant Typhoon Vision",
      "sourceRank": 0,
      "ageDays": 0
    },
    {
      "id": "md-meta:/master-v/june-2026/branded/sebastian/tn8bC/",
      "title": "Branded",
      "url": "https://www.masterduelmeta.com/master-v/june-2026/branded/sebastian/tn8bC/",
      "source": "Master Duel Meta Top Decks",
      "format": "md",
      "creator": "Sebastian",
      "tournament": "Master V",
      "placement": "",
      "date": "2026-06-22T16:17:49.113Z",
      "views": 0,
      "rating": 16,
      "engines": [
        "Dogmatika",
        "The Fallen & The Virtuous"
      ],
      "notes": "",
      "archetypes": [
        "Branded",
        "Dogmatika",
        "The Fallen & The Virtuous"
      ],
      "mainIds": [
        23434538,
        14558127,
        14558127,
        14558127,
        19304410,
        60303688,
        68468459,
        62962630,
        62962630,
        62962630,
        55273560,
        82489470,
        19096726,
        95515789,
        95515789,
        45883110,
        42141493,
        42141493,
        42141493,
        73819701,
        73819701,
        33854624,
        25451383,
        75500286,
        1984618,
        1984618,
        44362883,
        44362883,
        48130397,
        48130397,
        48130397,
        24224830,
        36637374,
        29948294,
        29948294,
        29948294,
        30271097,
        30271097,
        30271097,
        17751597
      ],
      "extraIds": [
        41373230,
        87746184,
        87746184,
        44146295,
        3410461,
        70534340,
        24915933,
        51409648,
        38811586,
        72578374,
        76666602,
        76666602,
        18666161,
        78397661,
        78397661
      ],
      "sideIds": [],
      "metaText": "Master Duel Meta Top Decks Master V Branded Dogmatika The Fallen & The Virtuous",
      "sourceRank": 0,
      "ageDays": 0
    },
    {
      "id": "md-meta:/master-v/june-2026/branded/harudes_./Tpz45/",
      "title": "Branded",
      "url": "https://www.masterduelmeta.com/master-v/june-2026/branded/harudes_./Tpz45/",
      "source": "Master Duel Meta Top Decks",
      "format": "md",
      "creator": "harudes_.",
      "tournament": "Master V",
      "placement": "",
      "date": "2026-06-22T16:17:45.279Z",
      "views": 0,
      "rating": 16,
      "engines": [
        "Dogmatika",
        "The Fallen & The Virtuous"
      ],
      "notes": "",
      "archetypes": [
        "Branded",
        "Dogmatika",
        "The Fallen & The Virtuous"
      ],
      "mainIds": [
        23434538,
        14558127,
        14558127,
        14558127,
        19304410,
        45484331,
        82489470,
        19096726,
        68468459,
        62962630,
        62962630,
        62962630,
        55273560,
        95515789,
        95515789,
        45883110,
        45883110,
        42141493,
        42141493,
        73819701,
        73819701,
        33854624,
        81555617,
        1984618,
        1984618,
        1984618,
        44362883,
        44362883,
        24224830,
        36637374,
        29948294,
        29948294,
        29948294,
        82738008,
        30271097,
        30271097,
        30271097,
        15693423,
        15693423,
        15693423
      ],
      "extraIds": [
        41373230,
        87746184,
        87746184,
        72272462,
        3410461,
        70534340,
        44146295,
        24915933,
        51409648,
        38811586,
        76666602,
        76666602,
        11321089,
        78397661
      ],
      "sideIds": [],
      "metaText": "Master Duel Meta Top Decks Master V Branded Dogmatika The Fallen & The Virtuous",
      "sourceRank": 0,
      "ageDays": 0
    },
    {
      "id": "md-meta:/master-v/june-2026/branded/flygon727/O4uEv/",
      "title": "Branded",
      "url": "https://www.masterduelmeta.com/master-v/june-2026/branded/flygon727/O4uEv/",
      "source": "Master Duel Meta Top Decks",
      "format": "md",
      "creator": "flygon727",
      "tournament": "Master V",
      "placement": "",
      "date": "2026-06-22T14:21:12.213Z",
      "views": 0,
      "rating": 16,
      "engines": [
        "The Fallen & The Virtuous"
      ],
      "notes": "",
      "archetypes": [
        "Branded",
        "The Fallen & The Virtuous"
      ],
      "mainIds": [
        23434538,
        14558127,
        14558127,
        14558127,
        19304410,
        19096726,
        60303688,
        68468459,
        62962630,
        62962630,
        62962630,
        55273560,
        55273560,
        95515789,
        95515789,
        45883110,
        42141493,
        42141493,
        42141493,
        73819701,
        73819701,
        25451383,
        75500286,
        44362883,
        44362883,
        48130397,
        48130397,
        48130397,
        24224830,
        24299458,
        24299458,
        24299458,
        36637374,
        29948294,
        29948294,
        29948294,
        30271097,
        30271097,
        30271097,
        81767888,
        17751597
      ],
      "extraIds": [
        54757758,
        92892239,
        41373230,
        87746184,
        87746184,
        3410461,
        70534340,
        44146295,
        24915933,
        24915933,
        51409648,
        76666602,
        76666602,
        18666161,
        78397661
      ],
      "sideIds": [],
      "metaText": "Master Duel Meta Top Decks Master V Branded The Fallen & The Virtuous",
      "sourceRank": 0,
      "ageDays": 0
    },
    {
      "id": "md-meta:/master-v/june-2026/branded/nanbawan/haU5m/",
      "title": "Branded",
      "url": "https://www.masterduelmeta.com/master-v/june-2026/branded/nanbawan/haU5m/",
      "source": "Master Duel Meta Top Decks",
      "format": "md",
      "creator": "Nanbawan",
      "tournament": "Master V",
      "placement": "",
      "date": "2026-06-22T07:34:56.058Z",
      "views": 0,
      "rating": 16,
      "engines": [
        "Dogmatika",
        "The Fallen & The Virtuous"
      ],
      "notes": "",
      "archetypes": [
        "Branded",
        "Dogmatika",
        "The Fallen & The Virtuous"
      ],
      "mainIds": [
        23434538,
        14558127,
        14558127,
        14558127,
        19304410,
        60303688,
        68468459,
        94395649,
        62962630,
        62962630,
        62962630,
        55273560,
        19096726,
        95515789,
        95515789,
        45883110,
        42141493,
        42141493,
        42141493,
        73819701,
        73819701,
        25451383,
        1984618,
        1984618,
        44362883,
        44362883,
        48130397,
        48130397,
        48130397,
        24224830,
        24299458,
        24299458,
        36637374,
        29948294,
        29948294,
        29948294,
        30271097,
        30271097,
        30271097,
        17751597
      ],
      "extraIds": [
        41209827,
        41373230,
        87746184,
        87746184,
        44146295,
        3410461,
        70534340,
        24915933,
        24915933,
        51409648,
        72578374,
        76666602,
        76666602,
        78397661,
        53971455
      ],
      "sideIds": [],
      "metaText": "Master Duel Meta Top Decks Master V Branded Dogmatika The Fallen & The Virtuous",
      "sourceRank": 0,
      "ageDays": 0
    },
    {
      "id": "md-meta:/master-i/june-2026/dracotail/luchomi/SiU_9/",
      "title": "Dracotail",
      "url": "https://www.masterduelmeta.com/master-i/june-2026/dracotail/luchomi/SiU_9/",
      "source": "Master Duel Meta Top Decks",
      "format": "md",
      "creator": "luchomi",
      "tournament": "Master I",
      "placement": "",
      "date": "2026-06-22T16:33:41.393Z",
      "views": 0,
      "rating": 16,
      "engines": [
        "Branded",
        "Fallen of the White Dragon",
        "The Fallen & The Virtuous"
      ],
      "notes": "",
      "archetypes": [
        "Dracotail",
        "Branded",
        "Fallen of the White Dragon",
        "The Fallen & The Virtuous"
      ],
      "mainIds": [
        23434538,
        84477320,
        14558127,
        14558127,
        14558127,
        7375867,
        7375867,
        7375867,
        68468459,
        55273560,
        55273560,
        95515789,
        95515789,
        42141493,
        42141493,
        42141493,
        75003700,
        73819701,
        73819701,
        1498449,
        1498449,
        1498449,
        70871153,
        70871153,
        44482554,
        44362883,
        44362883,
        6153210,
        6153210,
        6153210,
        32548318,
        48130397,
        48130397,
        48130397,
        30271097,
        30271097,
        30271097,
        5431722,
        69932023,
        80208225
      ],
      "extraIds": [
        79755671,
        41373230,
        87746184,
        87746184,
        44146295,
        3410461,
        51409648,
        38811586,
        72578374,
        33760966,
        33760966,
        89851827,
        76666602,
        78397661,
        70369116
      ],
      "sideIds": [],
      "metaText": "Master Duel Meta Top Decks Master I Dracotail Branded Fallen of the White Dragon The Fallen & The Virtuous",
      "sourceRank": 0,
      "ageDays": 0
    },
    {
      "id": "md-meta:/special-tournament/challenger-cup-eu-june-2026/13/dracotail/luvasy/8udn9/",
      "title": "Dracotail",
      "url": "https://www.masterduelmeta.com/special-tournament/challenger-cup-eu-june-2026/13/dracotail/luvasy/8udn9/",
      "source": "Master Duel Meta Top Decks",
      "format": "md",
      "creator": "Luvasy",
      "tournament": "Special Tournament",
      "placement": "Top 4",
      "date": "2026-06-22T13:59:26.663Z",
      "views": 0,
      "rating": 16,
      "engines": [
        "Branded",
        "Fallen of the White Dragon",
        "The Fallen & The Virtuous"
      ],
      "notes": "",
      "archetypes": [
        "Dracotail",
        "Branded",
        "Fallen of the White Dragon",
        "The Fallen & The Virtuous"
      ],
      "mainIds": [
        23434538,
        84477320,
        14558127,
        14558127,
        14558127,
        7375867,
        7375867,
        7375867,
        68468459,
        55273560,
        55273560,
        95515789,
        95515789,
        84192580,
        84192580,
        84192580,
        75003700,
        73819701,
        73819701,
        1498449,
        1498449,
        1498449,
        33854624,
        70871153,
        70871153,
        44482554,
        44362883,
        44362883,
        6153210,
        6153210,
        6153210,
        32548318,
        48130397,
        48130397,
        48130397,
        24224830,
        30271097,
        30271097,
        30271097,
        5431722,
        80208225
      ],
      "extraIds": [
        96334243,
        79755671,
        41373230,
        87746184,
        44146295,
        3410461,
        51409648,
        72578374,
        33760966,
        33760966,
        89851827,
        76666602,
        76666602,
        78397661,
        70369116
      ],
      "sideIds": [],
      "metaText": "Master Duel Meta Top Decks Special Tournament Dracotail Branded Fallen of the White Dragon The Fallen & The Virtuous",
      "sourceRank": 0,
      "ageDays": 0
    },
    {
      "id": "md-meta:/master-v/june-2026/dracotail/fud/63BzM/",
      "title": "Dracotail",
      "url": "https://www.masterduelmeta.com/master-v/june-2026/dracotail/fud/63BzM/",
      "source": "Master Duel Meta Top Decks",
      "format": "md",
      "creator": "Fud",
      "tournament": "Master V",
      "placement": "",
      "date": "2026-06-22T07:34:48.967Z",
      "views": 0,
      "rating": 16,
      "engines": [
        "Branded",
        "Fallen of the White Dragon",
        "The Fallen & The Virtuous"
      ],
      "notes": "",
      "archetypes": [
        "Dracotail",
        "Branded",
        "Fallen of the White Dragon",
        "The Fallen & The Virtuous"
      ],
      "mainIds": [
        23434538,
        84477320,
        14558127,
        14558127,
        14558127,
        73642296,
        73642296,
        73642296,
        7375867,
        7375867,
        7375867,
        68468459,
        55273560,
        55273560,
        95515789,
        95515789,
        42141493,
        42141493,
        42141493,
        75003700,
        73819701,
        73819701,
        1498449,
        1498449,
        1498449,
        33854624,
        70871153,
        70871153,
        44482554,
        44362883,
        44362883,
        6153210,
        6153210,
        6153210,
        32548318,
        30271097,
        30271097,
        30271097,
        5431722,
        80208225
      ],
      "extraIds": [
        79755671,
        87746184,
        87746184,
        44146295,
        3410461,
        70534340,
        51409648,
        38811586,
        72578374,
        33760966,
        33760966,
        89851827,
        76666602,
        78397661,
        70369116
      ],
      "sideIds": [],
      "metaText": "Master Duel Meta Top Decks Master V Dracotail Branded Fallen of the White Dragon The Fallen & The Virtuous",
      "sourceRank": 0,
      "ageDays": 0
    },
    {
      "id": "md-meta:/master-v/june-2026/elfnote/l/zxipH/",
      "title": "Elfnote",
      "url": "https://www.masterduelmeta.com/master-v/june-2026/elfnote/l/zxipH/",
      "source": "Master Duel Meta Top Decks",
      "format": "md",
      "creator": "L",
      "tournament": "Master V",
      "placement": "",
      "date": "2026-06-22T07:42:01.731Z",
      "views": 0,
      "rating": 2,
      "engines": [
        "Dragoon",
        "Azamina",
        "Fiendsmith",
        "Dark Magician of Destruction"
      ],
      "notes": "",
      "archetypes": [
        "Elfnote",
        "Dragoon",
        "Azamina",
        "Fiendsmith",
        "Dark Magician of Destruction"
      ],
      "mainIds": [
        94145021,
        94145021,
        9742784,
        12375297,
        12375297,
        23434538,
        59438930,
        14558127,
        14558127,
        14558127,
        68468459,
        45484331,
        42141493,
        42141493,
        42141493,
        84192580,
        97556336,
        97556336,
        60764609,
        85976588,
        13597785,
        13597785,
        13597785,
        56651978,
        59581480,
        59581480,
        59581480,
        72270339,
        72270339,
        72270339,
        94845588,
        48739627,
        48739627,
        48739627,
        66328392,
        64491754,
        64491754,
        64491754,
        80845034,
        24224830,
        65681983,
        22283204,
        24299458,
        30271097,
        30271097,
        30271097,
        53329234,
        10045474,
        10045474,
        10045474,
        24092792
      ],
      "extraIds": [
        46396218,
        73391962,
        93860227,
        59400890,
        37818794,
        87746184,
        76666602,
        37675907,
        42302563,
        78397661,
        92519087,
        84815190,
        79559912,
        93039339,
        2463794
      ],
      "sideIds": [],
      "metaText": "Master Duel Meta Top Decks Master V Elfnote Dragoon Azamina Fiendsmith Dark Magician of Destruction",
      "sourceRank": 0,
      "ageDays": 0
    },
    {
      "id": "md-meta:/master-i/june-2026/enneacraft/bunnza.1/zBX1j/",
      "title": "Enneacraft",
      "url": "https://www.masterduelmeta.com/master-i/june-2026/enneacraft/bunnza.1/zBX1j/",
      "source": "Master Duel Meta Top Decks",
      "format": "md",
      "creator": "bunnza.1",
      "tournament": "Master I",
      "placement": "",
      "date": "2026-06-22T16:33:48.614Z",
      "views": 0,
      "rating": 6.5,
      "engines": [
        "The Fallen & The Virtuous"
      ],
      "notes": "",
      "archetypes": [
        "Enneacraft",
        "The Fallen & The Virtuous"
      ],
      "mainIds": [
        92171126,
        92171126,
        92171126,
        29570824,
        29570824,
        29570824,
        55965529,
        55965529,
        55965529,
        56187077,
        56187077,
        56187077,
        44716748,
        44716748,
        44716748,
        82359538,
        82359538,
        82359538,
        81237046,
        28454232,
        28454232,
        28454232,
        71801447,
        71801447,
        54842941,
        54842941,
        54842941,
        54020393,
        54020393,
        54020393,
        19504025,
        19504025,
        80015408,
        80015408,
        17621695,
        17621695,
        24224830,
        30271097,
        30271097,
        30271097
      ],
      "extraIds": [
        11765832,
        87746184,
        70534340,
        78397661,
        95113856,
        9940036,
        90303227,
        90448279,
        93039339,
        65741786,
        29301450,
        33781156
      ],
      "sideIds": [],
      "metaText": "Master Duel Meta Top Decks Master I Enneacraft The Fallen & The Virtuous",
      "sourceRank": 0,
      "ageDays": 0
    },
    {
      "id": "md-meta:/master-v/june-2026/enneacraft/mas-bunga/L_9wp/",
      "title": "Enneacraft",
      "url": "https://www.masterduelmeta.com/master-v/june-2026/enneacraft/mas-bunga/L_9wp/",
      "source": "Master Duel Meta Top Decks",
      "format": "md",
      "creator": "Mas Bunga",
      "tournament": "Master V",
      "placement": "",
      "date": "2026-06-22T16:17:53.075Z",
      "views": 0,
      "rating": 6.5,
      "engines": [
        "The Fallen & The Virtuous",
        "Zaborg the Mega Monarch"
      ],
      "notes": "",
      "archetypes": [
        "Enneacraft",
        "The Fallen & The Virtuous",
        "Zaborg the Mega Monarch"
      ],
      "mainIds": [
        92171126,
        92171126,
        92171126,
        29570824,
        29570824,
        29570824,
        55965529,
        55965529,
        56187077,
        56187077,
        56187077,
        44716748,
        44716748,
        23434538,
        87602890,
        82359538,
        82359538,
        81237046,
        28454232,
        28454232,
        71801447,
        54842941,
        54842941,
        54842941,
        25311006,
        25311006,
        54020393,
        54020393,
        54020393,
        19504025,
        80015408,
        80015408,
        80015408,
        17621695,
        17621695,
        19739265,
        19739265,
        19739265,
        30271097,
        30271097
      ],
      "extraIds": [
        59531356,
        11765832,
        87746184,
        93125329,
        80032567,
        80032567,
        98506199,
        4891376,
        78397661,
        17548456,
        17548456,
        52553102,
        52553102,
        9940036,
        26847978
      ],
      "sideIds": [],
      "metaText": "Master Duel Meta Top Decks Master V Enneacraft The Fallen & The Virtuous Zaborg the Mega Monarch",
      "sourceRank": 0,
      "ageDays": 0
    },
    {
      "id": "md-meta:/master-i/june-2026/kewl-tune/³jwalking/Pi2TO/",
      "title": "Kewl Tune",
      "url": "https://www.masterduelmeta.com/master-i/june-2026/kewl-tune/³jwalking/Pi2TO/",
      "source": "Master Duel Meta Top Decks",
      "format": "md",
      "creator": "³JWalking",
      "tournament": "Master I",
      "placement": "",
      "date": "2026-06-22T16:33:38.074Z",
      "views": 0,
      "rating": 17,
      "engines": [
        "The Fallen & The Virtuous"
      ],
      "notes": "",
      "archetypes": [
        "Kewl Tune",
        "The Fallen & The Virtuous"
      ],
      "mainIds": [
        97268402,
        97268402,
        97268402,
        17209452,
        17209452,
        17209452,
        23434538,
        43904702,
        16509007,
        16509007,
        16509007,
        59438930,
        59438930,
        14558127,
        14558127,
        14558127,
        73642296,
        73642296,
        16387555,
        16387555,
        16387555,
        89392810,
        89392810,
        89392810,
        35261759,
        35261759,
        99243014,
        97474300,
        97474300,
        14442329,
        24224830,
        78058681,
        78058681,
        78058681,
        30271097,
        30271097,
        30271097,
        10045474,
        10045474,
        10045474
      ],
      "extraIds": [
        87746184,
        42781164,
        42781164,
        39576656,
        15665977,
        15665977,
        88170262,
        88170262,
        41069676,
        41069676,
        4891376,
        78397661,
        22850702,
        65961304,
        93039339
      ],
      "sideIds": [],
      "metaText": "Master Duel Meta Top Decks Master I Kewl Tune The Fallen & The Virtuous",
      "sourceRank": 0,
      "ageDays": 0
    },
    {
      "id": "md-meta:/master-v/june-2026/r.b./킬육/t9F7o/",
      "title": "R.B.",
      "url": "https://www.masterduelmeta.com/master-v/june-2026/r.b./킬육/t9F7o/",
      "source": "Master Duel Meta Top Decks",
      "format": "md",
      "creator": "킬육",
      "tournament": "Master V",
      "placement": "",
      "date": "2026-06-22T16:18:03.726Z",
      "views": 0,
      "rating": 0,
      "engines": [
        "Sky Striker",
        "Clockwork",
        "Cyberdark",
        "The Fallen & The Virtuous"
      ],
      "notes": "",
      "archetypes": [
        "R.B.",
        "Sky Striker",
        "Clockwork",
        "Cyberdark",
        "The Fallen & The Virtuous"
      ],
      "mainIds": [
        94145021,
        94145021,
        1142880,
        23434538,
        23893227,
        23893227,
        23893227,
        14558127,
        14558127,
        14558127,
        82562802,
        82562802,
        82562802,
        6043161,
        5370235,
        42141493,
        42141493,
        42141493,
        33438265,
        56100345,
        79436874,
        81794107,
        17188206,
        10604644,
        44573911,
        5109321,
        5109321,
        5109321,
        37630732,
        63166095,
        63166095,
        60600126,
        60600126,
        60600126,
        25311006,
        78710386,
        78710386,
        78710386,
        16066654,
        64753988,
        64753988,
        84797028,
        24224830,
        52340444,
        98338152,
        65681983,
        30271097,
        30271097,
        30271097,
        43450363,
        79859067
      ],
      "extraIds": [
        8963089,
        87746184,
        78397661,
        6821579,
        6821579,
        80071619,
        80071619,
        32216688,
        32216688,
        63288573,
        12421694,
        41739381,
        41739381,
        25072579,
        63013339
      ],
      "sideIds": [],
      "metaText": "Master Duel Meta Top Decks Master V R.B. Sky Striker Clockwork Cyberdark The Fallen & The Virtuous",
      "sourceRank": 0,
      "ageDays": 0
    },
    {
      "id": "md-meta:/master-i/june-2026/super-quant/masuta-bikuta/ZuWKd/",
      "title": "Super Quant",
      "url": "https://www.masterduelmeta.com/master-i/june-2026/super-quant/masuta-bikuta/ZuWKd/",
      "source": "Master Duel Meta Top Decks",
      "format": "md",
      "creator": "Masuta Bikuta",
      "tournament": "Master I",
      "placement": "",
      "date": "2026-06-22T07:38:35.482Z",
      "views": 0,
      "rating": 0,
      "engines": [
        "Fiendsmith",
        "Radiant Typhoon Vision",
        "The Fallen & The Virtuous"
      ],
      "notes": "",
      "archetypes": [
        "Super Quant",
        "Fiendsmith",
        "Radiant Typhoon Vision",
        "The Fallen & The Virtuous"
      ],
      "mainIds": [
        97651498,
        94145021,
        94145021,
        58753372,
        58753372,
        66646087,
        66646087,
        23434538,
        12369277,
        12369277,
        14558127,
        14558127,
        14558127,
        85374678,
        28803166,
        59975920,
        59975920,
        60764609,
        73422829,
        73422829,
        92034192,
        92034192,
        72332074,
        98567237,
        10424147,
        67723438,
        67723438,
        67723438,
        24224830,
        24299458,
        24299458,
        24299458,
        20508881,
        20508881,
        30271097,
        30271097,
        30271097,
        47819246
      ],
      "extraIds": [
        93860227,
        87746184,
        78397661,
        22850702,
        85252081,
        11646785,
        57031794,
        57031794,
        79559912,
        57450198,
        84025439,
        90448279,
        2463794,
        29301450,
        71818935
      ],
      "sideIds": [],
      "metaText": "Master Duel Meta Top Decks Master I Super Quant Fiendsmith Radiant Typhoon Vision The Fallen & The Virtuous",
      "sourceRank": 0,
      "ageDays": 0
    },
    {
      "id": "md-meta:/master-i/june-2026/thunder-dragon/gadgetbug/MeOa6/",
      "title": "Thunder Dragon",
      "url": "https://www.masterduelmeta.com/master-i/june-2026/thunder-dragon/gadgetbug/MeOa6/",
      "source": "Master Duel Meta Top Decks",
      "format": "md",
      "creator": "GadgetBug",
      "tournament": "Master I",
      "placement": "",
      "date": "2026-06-22T16:33:44.643Z",
      "views": 0,
      "rating": 0,
      "engines": [
        "Branded",
        "Bystial",
        "Fallen of the White Dragon",
        "The Fallen & The Virtuous"
      ],
      "notes": "",
      "archetypes": [
        "Thunder Dragon",
        "Branded",
        "Bystial",
        "Fallen of the White Dragon",
        "The Fallen & The Virtuous"
      ],
      "mainIds": [
        23434538,
        14558127,
        14558127,
        44586426,
        44586426,
        44586426,
        68468459,
        55273560,
        55273560,
        95515789,
        42141493,
        42141493,
        73819701,
        73819701,
        31786629,
        31786629,
        31786629,
        56713174,
        56713174,
        56713174,
        83107873,
        29596581,
        6637331,
        6637331,
        33854624,
        60242223,
        72656408,
        72656408,
        72656408,
        32731036,
        32731036,
        75500286,
        95238394,
        44362883,
        44362883,
        34090915,
        24299458,
        24299458,
        24299458,
        30271097,
        30271097,
        30271097
      ],
      "extraIds": [
        15291624,
        15291624,
        87746184,
        87746184,
        44146295,
        3410461,
        70534340,
        24915933,
        72578374,
        76666602,
        41685633,
        78397661,
        22850702,
        65741786,
        29301450
      ],
      "sideIds": [],
      "metaText": "Master Duel Meta Top Decks Master I Thunder Dragon Branded Bystial Fallen of the White Dragon The Fallen & The Virtuous",
      "sourceRank": 0,
      "ageDays": 0
    },
    {
      "id": "md-meta:/wcs-2026-qualifiers-dlv.-max/june-2026/b.e.s./diocrice/qJ9pv/",
      "title": "B.E.S.",
      "url": "https://www.masterduelmeta.com/wcs-2026-qualifiers-dlv.-max/june-2026/b.e.s./diocrice/qJ9pv/",
      "source": "Master Duel Meta Top Decks",
      "format": "md",
      "creator": "Diocrice",
      "tournament": "WCS 2026 DLv. Max",
      "placement": "",
      "date": "2026-06-21T23:58:09.713Z",
      "views": 0,
      "rating": 0,
      "engines": [
        "Clockwork",
        "The Fallen & The Virtuous"
      ],
      "notes": "",
      "archetypes": [
        "B.E.S.",
        "Clockwork",
        "The Fallen & The Virtuous"
      ],
      "mainIds": [
        23893227,
        23893227,
        23893227,
        30012506,
        10642488,
        78910832,
        22790789,
        44954628,
        82821760,
        82821760,
        84257883,
        84257883,
        33093439,
        5121528,
        5121528,
        5121528,
        41516133,
        41516133,
        41516133,
        38527680,
        38527680,
        38527680,
        18144507,
        19613556,
        67169062,
        86686671,
        60600126,
        60600126,
        60600126,
        14532163,
        14532163,
        14532163,
        25311006,
        2263869,
        2263869,
        2263869,
        35269904,
        35269904,
        35269904,
        15735108,
        66236707,
        66236707,
        66236707,
        33017964,
        975299,
        975299,
        975299,
        4909946,
        4909946,
        4909946,
        66947414,
        66947414,
        66947414,
        84797028,
        48130397,
        48130397,
        48130397,
        30271097,
        30271097,
        30271097
      ],
      "extraIds": [
        54757758,
        96334243,
        11765832,
        79229522,
        87746184,
        76666602,
        87116928,
        93125329,
        98506199,
        78397661,
        61399402,
        9940036,
        93039339,
        41739381,
        33781156
      ],
      "sideIds": [],
      "metaText": "Master Duel Meta Top Decks WCS 2026 DLv. Max B.E.S. Clockwork The Fallen & The Virtuous",
      "sourceRank": 0,
      "ageDays": 1
    },
    {
      "id": "md-meta:/wcs-regional-qualifiers-win-streaks/june-2026/branded/beacons/C3pbH/",
      "title": "Branded",
      "url": "https://www.masterduelmeta.com/wcs-regional-qualifiers-win-streaks/june-2026/branded/beacons/C3pbH/",
      "source": "Master Duel Meta Top Decks",
      "format": "md",
      "creator": "Beacons",
      "tournament": "WCS Regional Qualifiers Win Streaks",
      "placement": "",
      "date": "2026-06-22T02:33:40.962Z",
      "views": 0,
      "rating": 16,
      "engines": [
        "Dogmatika",
        "The Fallen & The Virtuous"
      ],
      "notes": "",
      "archetypes": [
        "Branded",
        "Dogmatika",
        "The Fallen & The Virtuous"
      ],
      "mainIds": [
        23434538,
        14558127,
        14558127,
        14558127,
        19304410,
        60303688,
        68468459,
        62962630,
        62962630,
        62962630,
        55273560,
        82489470,
        19096726,
        95515789,
        95515789,
        45883110,
        42141493,
        42141493,
        42141493,
        73819701,
        73819701,
        33854624,
        25451383,
        75500286,
        1984618,
        1984618,
        44362883,
        44362883,
        48130397,
        48130397,
        48130397,
        24224830,
        36637374,
        29948294,
        29948294,
        29948294,
        30271097,
        30271097,
        30271097,
        17751597
      ],
      "extraIds": [
        54757758,
        41373230,
        87746184,
        87746184,
        44146295,
        3410461,
        70534340,
        24915933,
        51409648,
        72578374,
        76666602,
        76666602,
        18666161,
        78397661
      ],
      "sideIds": [],
      "metaText": "Master Duel Meta Top Decks WCS Regional Qualifiers Win Streaks Branded Dogmatika The Fallen & The Virtuous",
      "sourceRank": 0,
      "ageDays": 1
    },
    {
      "id": "md-meta:/wcs-2026-qualifiers-dlv.-max/june-2026/branded/yurica/-UGEP/",
      "title": "Branded",
      "url": "https://www.masterduelmeta.com/wcs-2026-qualifiers-dlv.-max/june-2026/branded/yurica/-UGEP/",
      "source": "Master Duel Meta Top Decks",
      "format": "md",
      "creator": "yurica",
      "tournament": "WCS 2026 DLv. Max",
      "placement": "",
      "date": "2026-06-22T02:31:59.636Z",
      "views": 0,
      "rating": 16,
      "engines": [
        "Dogmatika",
        "The Fallen & The Virtuous"
      ],
      "notes": "",
      "archetypes": [
        "Branded",
        "Dogmatika",
        "The Fallen & The Virtuous"
      ],
      "mainIds": [
        94145021,
        94145021,
        23434538,
        14558127,
        14558127,
        14558127,
        19304410,
        60303688,
        68468459,
        62962630,
        62962630,
        62962630,
        55273560,
        82489470,
        63542003,
        95515789,
        95515789,
        45883110,
        42141493,
        42141493,
        73819701,
        73819701,
        33854624,
        60242223,
        60242223,
        1984618,
        1984618,
        1984618,
        25311006,
        44362883,
        44362883,
        24224830,
        36637374,
        29948294,
        29948294,
        29948294,
        30271097,
        30271097,
        30271097,
        17751597
      ],
      "extraIds": [
        92892239,
        41373230,
        87746184,
        87746184,
        44146295,
        3410461,
        70534340,
        24915933,
        51409648,
        38811586,
        76666602,
        18666161,
        74586817,
        13076804,
        78397661
      ],
      "sideIds": [],
      "metaText": "Master Duel Meta Top Decks WCS 2026 DLv. Max Branded Dogmatika The Fallen & The Virtuous",
      "sourceRank": 0,
      "ageDays": 1
    },
    {
      "id": "md-meta:/meta-weekly/230/branded/monstermns/geXg3/",
      "title": "Branded",
      "url": "https://www.masterduelmeta.com/meta-weekly/230/branded/monstermns/geXg3/",
      "source": "Master Duel Meta Top Decks",
      "format": "md",
      "creator": "monsterMns",
      "tournament": "Meta Weekly",
      "placement": "Top 4",
      "date": "2026-06-22T01:56:32.906Z",
      "views": 0,
      "rating": 16,
      "engines": [
        "That Grass Looks Greener",
        "The Fallen & The Virtuous"
      ],
      "notes": "",
      "archetypes": [
        "Branded",
        "That Grass Looks Greener",
        "The Fallen & The Virtuous"
      ],
      "mainIds": [
        94145021,
        94145021,
        36577931,
        23434538,
        37961969,
        19304410,
        15381421,
        15381421,
        60303688,
        68468459,
        62962630,
        62962630,
        55273560,
        45484331,
        82489470,
        19096726,
        95515789,
        95515789,
        45883110,
        73819701,
        73819701,
        33854624,
        60242223,
        60242223,
        69680031,
        25451383,
        25451383,
        24226942,
        32731036,
        30394645,
        47082621,
        58577036,
        58577036,
        58577036,
        75500286,
        11110587,
        6498706,
        25311006,
        34995106,
        44362883,
        44362883,
        81439173,
        35269904,
        18973184,
        48130397,
        48130397,
        36637374,
        36637374,
        36637374,
        29948294,
        29948294,
        29948294,
        82738008,
        72554664,
        30271097,
        30271097,
        81767888,
        6763530,
        43331750,
        17751597
      ],
      "extraIds": [
        92892239,
        41373230,
        87746184,
        72272462,
        44146295,
        3410461,
        70534340,
        24915933,
        51409648,
        38811586,
        72578374,
        93053159,
        76666602,
        19652159,
        78397661
      ],
      "sideIds": [],
      "metaText": "Master Duel Meta Top Decks Meta Weekly Branded That Grass Looks Greener The Fallen & The Virtuous",
      "sourceRank": 0,
      "ageDays": 1
    },
    {
      "id": "md-meta:/meta-weekly/230/branded/moi/ubIcx/",
      "title": "Branded",
      "url": "https://www.masterduelmeta.com/meta-weekly/230/branded/moi/ubIcx/",
      "source": "Master Duel Meta Top Decks",
      "format": "md",
      "creator": "Moi",
      "tournament": "Meta Weekly",
      "placement": "Top 8",
      "date": "2026-06-22T01:56:26.369Z",
      "views": 0,
      "rating": 16,
      "engines": [
        "Dogmatika",
        "The Fallen & The Virtuous"
      ],
      "notes": "",
      "archetypes": [
        "Branded",
        "Dogmatika",
        "The Fallen & The Virtuous"
      ],
      "mainIds": [
        23434538,
        14558127,
        14558127,
        14558127,
        19304410,
        60303688,
        68468459,
        94395649,
        62962630,
        62962630,
        62962630,
        55273560,
        82489470,
        19096726,
        95515789,
        95515789,
        45883110,
        42141493,
        42141493,
        42141493,
        73819701,
        73819701,
        33854624,
        25451383,
        1984618,
        1984618,
        44362883,
        44362883,
        48130397,
        48130397,
        48130397,
        24224830,
        36637374,
        29948294,
        29948294,
        29948294,
        30271097,
        30271097,
        30271097,
        17751597
      ],
      "extraIds": [
        96334243,
        41373230,
        87746184,
        87746184,
        44146295,
        3410461,
        70534340,
        24915933,
        51409648,
        72578374,
        76666602,
        76666602,
        18666161,
        78397661
      ],
      "sideIds": [],
      "metaText": "Master Duel Meta Top Decks Meta Weekly Branded Dogmatika The Fallen & The Virtuous",
      "sourceRank": 0,
      "ageDays": 1
    },
    {
      "id": "md-meta:/meta-weekly/230/branded/goran-gajic/bm4So/",
      "title": "Branded",
      "url": "https://www.masterduelmeta.com/meta-weekly/230/branded/goran-gajic/bm4So/",
      "source": "Master Duel Meta Top Decks",
      "format": "md",
      "creator": "Goran Gajic",
      "tournament": "Meta Weekly",
      "placement": "Top 16",
      "date": "2026-06-22T01:56:19.797Z",
      "views": 0,
      "rating": 16,
      "engines": [
        "Dogmatika",
        "The Fallen & The Virtuous"
      ],
      "notes": "",
      "archetypes": [
        "Branded",
        "Dogmatika",
        "The Fallen & The Virtuous"
      ],
      "mainIds": [
        23434538,
        14558127,
        14558127,
        14558127,
        60303688,
        68468459,
        62962630,
        62962630,
        62962630,
        55273560,
        55273560,
        82489470,
        19096726,
        95515789,
        95515789,
        45883110,
        42141493,
        42141493,
        42141493,
        73819701,
        73819701,
        25451383,
        1984618,
        1984618,
        1984618,
        44362883,
        44362883,
        48130397,
        48130397,
        48130397,
        24224830,
        36637374,
        29948294,
        29948294,
        29948294,
        30271097,
        30271097,
        30271097,
        81767888,
        17751597
      ],
      "extraIds": [
        41373230,
        87746184,
        87746184,
        6855503,
        44146295,
        3410461,
        70534340,
        24915933,
        24915933,
        51409648,
        72578374,
        76666602,
        76666602,
        18666161,
        78397661
      ],
      "sideIds": [],
      "metaText": "Master Duel Meta Top Decks Meta Weekly Branded Dogmatika The Fallen & The Virtuous",
      "sourceRank": 0,
      "ageDays": 1
    },
    {
      "id": "md-meta:/meta-weekly/230/branded/milito-22/VkBCf/",
      "title": "Branded",
      "url": "https://www.masterduelmeta.com/meta-weekly/230/branded/milito-22/VkBCf/",
      "source": "Master Duel Meta Top Decks",
      "format": "md",
      "creator": "Milito-22",
      "tournament": "Meta Weekly",
      "placement": "Top 16",
      "date": "2026-06-22T01:56:16.489Z",
      "views": 0,
      "rating": 16,
      "engines": [
        "Dogmatika",
        "The Fallen & The Virtuous"
      ],
      "notes": "",
      "archetypes": [
        "Branded",
        "Dogmatika",
        "The Fallen & The Virtuous"
      ],
      "mainIds": [
        23434538,
        14558127,
        19304410,
        60303688,
        68468459,
        62962630,
        62962630,
        62962630,
        55273560,
        55273560,
        95515789,
        95515789,
        45883110,
        42141493,
        42141493,
        42141493,
        73819701,
        73819701,
        25451383,
        25451383,
        1984618,
        1984618,
        25311006,
        25311006,
        44362883,
        44362883,
        48130397,
        48130397,
        48130397,
        24224830,
        24299458,
        24299458,
        36637374,
        29948294,
        29948294,
        29948294,
        30271097,
        30271097,
        30271097,
        17751597
      ],
      "extraIds": [
        54757758,
        11765832,
        41373230,
        87746184,
        87746184,
        44146295,
        3410461,
        70534340,
        24915933,
        51409648,
        72578374,
        76666602,
        76666602,
        18666161,
        78397661
      ],
      "sideIds": [],
      "metaText": "Master Duel Meta Top Decks Meta Weekly Branded Dogmatika The Fallen & The Virtuous",
      "sourceRank": 0,
      "ageDays": 1
    },
    {
      "id": "md-meta:/master-i/june-2026/branded/ely/MYa1C/",
      "title": "Branded",
      "url": "https://www.masterduelmeta.com/master-i/june-2026/branded/ely/MYa1C/",
      "source": "Master Duel Meta Top Decks",
      "format": "md",
      "creator": "Ely",
      "tournament": "Master I",
      "placement": "",
      "date": "2026-06-21T23:57:01.262Z",
      "views": 0,
      "rating": 16,
      "engines": [
        "Dogmatika",
        "The Fallen & The Virtuous"
      ],
      "notes": "",
      "archetypes": [
        "Branded",
        "Dogmatika",
        "The Fallen & The Virtuous"
      ],
      "mainIds": [
        23434538,
        14558127,
        14558127,
        14558127,
        19304410,
        60303688,
        68468459,
        62962630,
        62962630,
        62962630,
        55273560,
        55273560,
        82489470,
        19096726,
        95515789,
        95515789,
        45883110,
        42141493,
        42141493,
        42141493,
        73819701,
        73819701,
        75500286,
        1984618,
        1984618,
        44362883,
        44362883,
        48130397,
        48130397,
        48130397,
        24224830,
        24299458,
        24299458,
        29948294,
        29948294,
        29948294,
        30271097,
        30271097,
        30271097,
        17751597
      ],
      "extraIds": [
        54757758,
        41373230,
        87746184,
        87746184,
        44146295,
        3410461,
        70534340,
        24915933,
        51409648,
        72578374,
        76666602,
        76666602,
        18666161,
        78397661
      ],
      "sideIds": [],
      "metaText": "Master Duel Meta Top Decks Master I Branded Dogmatika The Fallen & The Virtuous",
      "sourceRank": 0,
      "ageDays": 1
    },
    {
      "id": "md-meta:/master-v/june-2026/branded/md_monarch/WqeBU/",
      "title": "Branded",
      "url": "https://www.masterduelmeta.com/master-v/june-2026/branded/md_monarch/WqeBU/",
      "source": "Master Duel Meta Top Decks",
      "format": "md",
      "creator": "MD_Monarch",
      "tournament": "Master V",
      "placement": "",
      "date": "2026-06-21T20:42:18.904Z",
      "views": 0,
      "rating": 16,
      "engines": [
        "Dogmatika",
        "The Fallen & The Virtuous"
      ],
      "notes": "",
      "archetypes": [
        "Branded",
        "Dogmatika",
        "The Fallen & The Virtuous"
      ],
      "mainIds": [
        23434538,
        14558127,
        14558127,
        14558127,
        19304410,
        94395649,
        45484331,
        82489470,
        19096726,
        60303688,
        68468459,
        62962630,
        62962630,
        55273560,
        95515789,
        95515789,
        45883110,
        42141493,
        42141493,
        42141493,
        73819701,
        73819701,
        33854624,
        25451383,
        1984618,
        1984618,
        44362883,
        44362883,
        24224830,
        36637374,
        29948294,
        29948294,
        29948294,
        48130397,
        48130397,
        48130397,
        30271097,
        30271097,
        30271097,
        17751597
      ],
      "extraIds": [
        41373230,
        87746184,
        87746184,
        3410461,
        70534340,
        44146295,
        24915933,
        51409648,
        72578374,
        89851827,
        76666602,
        76666602,
        18666161,
        78397661
      ],
      "sideIds": [],
      "metaText": "Master Duel Meta Top Decks Master V Branded Dogmatika The Fallen & The Virtuous",
      "sourceRank": 0,
      "ageDays": 1
    },
    {
      "id": "md-meta:/wcs-2026-qualifiers-dlv.-max/june-2026/centur-ion/q354zq23h257/TI-R_/",
      "title": "Centur-Ion",
      "url": "https://www.masterduelmeta.com/wcs-2026-qualifiers-dlv.-max/june-2026/centur-ion/q354zq23h257/TI-R_/",
      "source": "Master Duel Meta Top Decks",
      "format": "md",
      "creator": "q354zq23h257",
      "tournament": "WCS 2026 DLv. Max",
      "placement": "",
      "date": "2026-06-21T23:58:23.219Z",
      "views": 0,
      "rating": 1,
      "engines": [
        "Bystial",
        "Fallen of the White Dragon",
        "The Fallen & The Virtuous"
      ],
      "notes": "",
      "archetypes": [
        "Centur-Ion",
        "Bystial",
        "Fallen of the White Dragon",
        "The Fallen & The Virtuous"
      ],
      "mainIds": [
        97268402,
        97268402,
        97268402,
        23434538,
        59438930,
        14558127,
        14558127,
        14558127,
        73642296,
        73642296,
        73642296,
        52038441,
        55273560,
        68468459,
        15005145,
        15005145,
        15005145,
        42493140,
        42493140,
        96030710,
        73819701,
        73819701,
        6637331,
        33854624,
        60242223,
        72656408,
        32731036,
        97698279,
        41371602,
        41371602,
        41371602,
        34090915,
        24224830,
        77765207,
        77765207,
        77765207,
        92907248,
        30271097,
        30271097,
        40155014
      ],
      "extraIds": [
        41373230,
        87746184,
        44146295,
        3410461,
        8841431,
        78397661,
        84815190,
        22850702,
        27572350,
        21123811,
        21123811,
        63436931,
        71858682,
        15982593,
        24361622
      ],
      "sideIds": [],
      "metaText": "Master Duel Meta Top Decks WCS 2026 DLv. Max Centur-Ion Bystial Fallen of the White Dragon The Fallen & The Virtuous",
      "sourceRank": 0,
      "ageDays": 1
    },
    {
      "id": "md-meta:/meta-weekly/230/dracotail/burd/3IB4a/",
      "title": "Dracotail",
      "url": "https://www.masterduelmeta.com/meta-weekly/230/dracotail/burd/3IB4a/",
      "source": "Master Duel Meta Top Decks",
      "format": "md",
      "creator": "burd",
      "tournament": "Meta Weekly",
      "placement": "Top 8",
      "date": "2026-06-22T01:56:31.164Z",
      "views": 0,
      "rating": 16,
      "engines": [
        "Branded",
        "Fallen of the White Dragon",
        "The Fallen & The Virtuous"
      ],
      "notes": "",
      "archetypes": [
        "Dracotail",
        "Branded",
        "Fallen of the White Dragon",
        "The Fallen & The Virtuous"
      ],
      "mainIds": [
        23434538,
        84477320,
        14558127,
        14558127,
        14558127,
        7375867,
        7375867,
        7375867,
        68468459,
        55273560,
        95515789,
        95515789,
        42141493,
        42141493,
        42141493,
        75003700,
        73819701,
        73819701,
        1498449,
        1498449,
        1498449,
        33854624,
        70871153,
        70871153,
        70871153,
        44482554,
        25451383,
        44362883,
        44362883,
        6153210,
        6153210,
        6153210,
        32548318,
        24299458,
        24299458,
        30271097,
        30271097,
        5431722,
        69932023,
        80208225
      ],
      "extraIds": [
        79755671,
        87746184,
        44146295,
        3410461,
        70534340,
        51409648,
        38811586,
        72578374,
        33760966,
        33760966,
        33760966,
        89851827,
        76666602,
        78397661,
        70369116
      ],
      "sideIds": [],
      "metaText": "Master Duel Meta Top Decks Meta Weekly Dracotail Branded Fallen of the White Dragon The Fallen & The Virtuous",
      "sourceRank": 0,
      "ageDays": 1
    },
    {
      "id": "md-meta:/meta-weekly/230/dracotail/modar-/APOSU/",
      "title": "Dracotail",
      "url": "https://www.masterduelmeta.com/meta-weekly/230/dracotail/modar-/APOSU/",
      "source": "Master Duel Meta Top Decks",
      "format": "md",
      "creator": "Modar ",
      "tournament": "Meta Weekly",
      "placement": "Top 8",
      "date": "2026-06-22T01:56:29.703Z",
      "views": 0,
      "rating": 16,
      "engines": [
        "Branded",
        "Fallen of the White Dragon",
        "The Fallen & The Virtuous"
      ],
      "notes": "",
      "archetypes": [
        "Dracotail",
        "Branded",
        "Fallen of the White Dragon",
        "The Fallen & The Virtuous"
      ],
      "mainIds": [
        97268402,
        94145021,
        94145021,
        23434538,
        84477320,
        14558127,
        14558127,
        14558127,
        7375867,
        7375867,
        7375867,
        68468459,
        55273560,
        55273560,
        95515789,
        95515789,
        75003700,
        73819701,
        73819701,
        1498449,
        1498449,
        1498449,
        70871153,
        70871153,
        44482554,
        12580477,
        18144507,
        19613556,
        14532163,
        14532163,
        44362883,
        44362883,
        6153210,
        6153210,
        6153210,
        32548318,
        24299458,
        24299458,
        30271097,
        30271097,
        30271097,
        5431722,
        69932023,
        80208225
      ],
      "extraIds": [
        79755671,
        87746184,
        87746184,
        44146295,
        3410461,
        70534340,
        51409648,
        38811586,
        72578374,
        33760966,
        33760966,
        89851827,
        76666602,
        78397661,
        70369116
      ],
      "sideIds": [],
      "metaText": "Master Duel Meta Top Decks Meta Weekly Dracotail Branded Fallen of the White Dragon The Fallen & The Virtuous",
      "sourceRank": 0,
      "ageDays": 1
    },
    {
      "id": "md-meta:/wcs-2026-qualifiers-dlv.-max/june-2026/dracotail/ball/b5iin/",
      "title": "Dracotail",
      "url": "https://www.masterduelmeta.com/wcs-2026-qualifiers-dlv.-max/june-2026/dracotail/ball/b5iin/",
      "source": "Master Duel Meta Top Decks",
      "format": "md",
      "creator": "ball",
      "tournament": "WCS 2026 DLv. Max",
      "placement": "",
      "date": "2026-06-21T23:58:16.550Z",
      "views": 0,
      "rating": 16,
      "engines": [
        "Branded",
        "Fallen of the White Dragon",
        "The Fallen & The Virtuous"
      ],
      "notes": "",
      "archetypes": [
        "Dracotail",
        "Branded",
        "Fallen of the White Dragon",
        "The Fallen & The Virtuous"
      ],
      "mainIds": [
        97268402,
        94145021,
        94145021,
        23434538,
        84477320,
        59438930,
        14558127,
        14558127,
        14558127,
        73642296,
        73642296,
        7375867,
        7375867,
        7375867,
        68468459,
        55273560,
        95515789,
        95515789,
        75003700,
        73819701,
        73819701,
        1498449,
        1498449,
        1498449,
        6637331,
        33854624,
        72656408,
        70871153,
        44482554,
        44362883,
        44362883,
        6153210,
        6153210,
        6153210,
        32548318,
        24224830,
        30271097,
        30271097,
        30271097,
        5431722,
        69932023,
        80208225
      ],
      "extraIds": [
        79755671,
        87746184,
        87746184,
        44146295,
        3410461,
        70534340,
        38811586,
        72578374,
        33760966,
        33760966,
        33760966,
        89851827,
        76666602,
        78397661,
        93039339
      ],
      "sideIds": [],
      "metaText": "Master Duel Meta Top Decks WCS 2026 DLv. Max Dracotail Branded Fallen of the White Dragon The Fallen & The Virtuous",
      "sourceRank": 0,
      "ageDays": 1
    },
    {
      "id": "md-meta:/wcs-regional-qualifiers-win-streaks/june-2026/dracotail/gazootm/2TMCd/",
      "title": "Dracotail",
      "url": "https://www.masterduelmeta.com/wcs-regional-qualifiers-win-streaks/june-2026/dracotail/gazootm/2TMCd/",
      "source": "Master Duel Meta Top Decks",
      "format": "md",
      "creator": "GazooTM",
      "tournament": "WCS Regional Qualifiers Win Streaks",
      "placement": "",
      "date": "2026-06-21T19:43:00.000Z",
      "views": 0,
      "rating": 16,
      "engines": [
        "Branded",
        "Fallen of the White Dragon",
        "The Fallen & The Virtuous"
      ],
      "notes": "",
      "archetypes": [
        "Dracotail",
        "Branded",
        "Fallen of the White Dragon",
        "The Fallen & The Virtuous"
      ],
      "mainIds": [
        97268402,
        23434538,
        84477320,
        14558127,
        14558127,
        14558127,
        73642296,
        7375867,
        7375867,
        7375867,
        68468459,
        55273560,
        55273560,
        95515789,
        95515789,
        42141493,
        42141493,
        75003700,
        73819701,
        73819701,
        1498449,
        1498449,
        1498449,
        33854624,
        70871153,
        70871153,
        44482554,
        25451383,
        44362883,
        44362883,
        6153210,
        6153210,
        6153210,
        32548318,
        24224830,
        30271097,
        30271097,
        5431722,
        69932023,
        80208225
      ],
      "extraIds": [
        79755671,
        41373230,
        87746184,
        87746184,
        44146295,
        3410461,
        51409648,
        38811586,
        72578374,
        33760966,
        33760966,
        89851827,
        76666602,
        78397661,
        70369116
      ],
      "sideIds": [],
      "metaText": "Master Duel Meta Top Decks WCS Regional Qualifiers Win Streaks Dracotail Branded Fallen of the White Dragon The Fallen & The Virtuous",
      "sourceRank": 0,
      "ageDays": 1
    },
    {
      "id": "md-meta:/meta-weekly/230/dragon-link/net777virus/-QWoV/",
      "title": "Dragon Link",
      "url": "https://www.masterduelmeta.com/meta-weekly/230/dragon-link/net777virus/-QWoV/",
      "source": "Master Duel Meta Top Decks",
      "format": "md",
      "creator": "Net777virus",
      "tournament": "Meta Weekly",
      "placement": "Top 16",
      "date": "2026-06-22T01:56:18.217Z",
      "views": 0,
      "rating": 1,
      "engines": [
        "New Rokket",
        "Radiant Typhoon Vision",
        "The Fallen & The Virtuous"
      ],
      "notes": "",
      "archetypes": [
        "Dragon Link",
        "New Rokket",
        "Radiant Typhoon Vision",
        "The Fallen & The Virtuous"
      ],
      "mainIds": [
        94145021,
        23434538,
        14558127,
        14558127,
        14558127,
        54143349,
        80538047,
        26655293,
        5969957,
        68464358,
        68464358,
        68464358,
        32476603,
        67127799,
        42141493,
        42141493,
        42141493,
        25554552,
        25554552,
        25554552,
        33854624,
        5560911,
        67748760,
        98937206,
        81439173,
        38129297,
        6556178,
        36668118,
        5318639,
        48130397,
        48130397,
        48130397,
        31443476,
        31443476,
        31443476,
        24224830,
        65681983,
        24299458,
        24299458,
        24299458,
        28958464,
        28958464,
        67115133,
        67115133,
        67115133,
        20508881,
        30271097,
        30271097,
        30271097,
        87607094
      ],
      "extraIds": [
        54757758,
        11765832,
        87746184,
        84464389,
        27548199,
        78397661,
        13143275,
        73539069,
        73539069,
        65741786,
        29301450,
        90011273,
        3957130,
        98630720,
        66452432
      ],
      "sideIds": [],
      "metaText": "Master Duel Meta Top Decks Meta Weekly Dragon Link New Rokket Radiant Typhoon Vision The Fallen & The Virtuous",
      "sourceRank": 0,
      "ageDays": 1
    },
    {
      "id": "md-meta:/master-i/june-2026/enneacraft/mlg_elmo/DyC8s/",
      "title": "Enneacraft",
      "url": "https://www.masterduelmeta.com/master-i/june-2026/enneacraft/mlg_elmo/DyC8s/",
      "source": "Master Duel Meta Top Decks",
      "format": "md",
      "creator": "MLG_ELMO",
      "tournament": "Master I",
      "placement": "",
      "date": "2026-06-22T02:31:13.180Z",
      "views": 0,
      "rating": 6.5,
      "engines": [
        "The Fallen & The Virtuous"
      ],
      "notes": "",
      "archetypes": [
        "Enneacraft",
        "The Fallen & The Virtuous"
      ],
      "mainIds": [
        92171126,
        92171126,
        92171126,
        29570824,
        29570824,
        29570824,
        55965529,
        55965529,
        55965529,
        56187077,
        56187077,
        56187077,
        44716748,
        44716748,
        44716748,
        82359538,
        82359538,
        82359538,
        81237046,
        28454232,
        28454232,
        28454232,
        71801447,
        71801447,
        71801447,
        54842941,
        54842941,
        54842941,
        54020393,
        54020393,
        54020393,
        19504025,
        19504025,
        80015408,
        80015408,
        80015408,
        17621695,
        30271097,
        30271097,
        30271097
      ],
      "extraIds": [
        31339260,
        52031567,
        52031567,
        87746184,
        76666602,
        42781164,
        15665977,
        15665977,
        82570174,
        78397661,
        39402797,
        47195442,
        31086840,
        31086840,
        93039339
      ],
      "sideIds": [],
      "metaText": "Master Duel Meta Top Decks Master I Enneacraft The Fallen & The Virtuous",
      "sourceRank": 0,
      "ageDays": 1
    },
    {
      "id": "md-meta:/wcs-2026-qualifiers-dlv.-max/june-2026/exosister/maiden-♡/BlTtN/",
      "title": "Exosister",
      "url": "https://www.masterduelmeta.com/wcs-2026-qualifiers-dlv.-max/june-2026/exosister/maiden-♡/BlTtN/",
      "source": "Master Duel Meta Top Decks",
      "format": "md",
      "creator": "maiden ♡",
      "tournament": "WCS 2026 DLv. Max",
      "placement": "",
      "date": "2026-06-21T19:46:00.000Z",
      "views": 0,
      "rating": 1,
      "engines": [
        "Dominus Purge",
        "The Fallen & The Virtuous"
      ],
      "notes": "",
      "archetypes": [
        "Exosister",
        "Dominus Purge",
        "The Fallen & The Virtuous"
      ],
      "mainIds": [
        23434538,
        14558127,
        14558127,
        14558127,
        16889337,
        16474916,
        16474916,
        16474916,
        79858629,
        5352328,
        43863925,
        43863925,
        37343995,
        37343995,
        37343995,
        42141493,
        42141493,
        42141493,
        9627299,
        9627299,
        9627299,
        91800273,
        25311006,
        52335937,
        52335937,
        52335937,
        77913594,
        77913594,
        77913594,
        24224830,
        30271097,
        30271097,
        10045474,
        10045474,
        10045474,
        77891946,
        197042,
        97045737,
        97045737,
        97045737
      ],
      "extraIds": [
        87746184,
        78397661,
        41524885,
        41524885,
        5530780,
        5530780,
        78135071,
        42741437,
        42741437,
        77675029,
        77675029,
        59242457,
        59242457,
        90448279,
        93039339
      ],
      "sideIds": [],
      "metaText": "Master Duel Meta Top Decks WCS 2026 DLv. Max Exosister Dominus Purge The Fallen & The Virtuous",
      "sourceRank": 0,
      "ageDays": 1
    },
    {
      "id": "md-meta:/wcs-2026-qualifiers-dlv.-max/june-2026/kewl-tune/márcio-🗡🗡🗡/hNUvS/",
      "title": "Kewl Tune",
      "url": "https://www.masterduelmeta.com/wcs-2026-qualifiers-dlv.-max/june-2026/kewl-tune/márcio-🗡🗡🗡/hNUvS/",
      "source": "Master Duel Meta Top Decks",
      "format": "md",
      "creator": "Márcio 🗡🗡🗡",
      "tournament": "WCS 2026 DLv. Max",
      "placement": "",
      "date": "2026-06-22T03:16:11.872Z",
      "views": 0,
      "rating": 17,
      "engines": [
        "The Fallen & The Virtuous"
      ],
      "notes": "",
      "archetypes": [
        "Kewl Tune",
        "The Fallen & The Virtuous"
      ],
      "mainIds": [
        97268402,
        97268402,
        97268402,
        94145021,
        94145021,
        17209452,
        17209452,
        17209452,
        23434538,
        43904702,
        16509007,
        16509007,
        16509007,
        59438930,
        14558127,
        14558127,
        14558127,
        73642296,
        73642296,
        16387555,
        16387555,
        16387555,
        89392810,
        89392810,
        89392810,
        42141493,
        42141493,
        42141493,
        99243014,
        97474300,
        97474300,
        14442329,
        24224830,
        65681983,
        78058681,
        78058681,
        78058681,
        30271097,
        30271097,
        30271097
      ],
      "extraIds": [
        87746184,
        42781164,
        42781164,
        39576656,
        15665977,
        15665977,
        88170262,
        88170262,
        41069676,
        4891376,
        78397661,
        22850702,
        65961304,
        65961304,
        93039339
      ],
      "sideIds": [],
      "metaText": "Master Duel Meta Top Decks WCS 2026 DLv. Max Kewl Tune The Fallen & The Virtuous",
      "sourceRank": 0,
      "ageDays": 1
    },
    {
      "id": "md-meta:/meta-weekly/230/kewl-tune/cofi/iRVDM/",
      "title": "Kewl Tune",
      "url": "https://www.masterduelmeta.com/meta-weekly/230/kewl-tune/cofi/iRVDM/",
      "source": "Master Duel Meta Top Decks",
      "format": "md",
      "creator": "cofi",
      "tournament": "Meta Weekly",
      "placement": "1st Place",
      "date": "2026-06-22T01:56:37.594Z",
      "views": 0,
      "rating": 17,
      "engines": [
        "The Fallen & The Virtuous"
      ],
      "notes": "",
      "archetypes": [
        "Kewl Tune",
        "The Fallen & The Virtuous"
      ],
      "mainIds": [
        97268402,
        97268402,
        97268402,
        17209452,
        17209452,
        17209452,
        23434538,
        43904702,
        16509007,
        16509007,
        16509007,
        59438930,
        14558127,
        14558127,
        14558127,
        73642296,
        73642296,
        52038441,
        52038441,
        16387555,
        16387555,
        16387555,
        89392810,
        89392810,
        89392810,
        25311006,
        99243014,
        97474300,
        97474300,
        14442329,
        14442329,
        24224830,
        78058681,
        78058681,
        78058681,
        30271097,
        30271097,
        10045474,
        10045474,
        10045474
      ],
      "extraIds": [
        87746184,
        42781164,
        42781164,
        42781164,
        39576656,
        15665977,
        15665977,
        88170262,
        88170262,
        41069676,
        41069676,
        4891376,
        78397661,
        65961304,
        93039339
      ],
      "sideIds": [],
      "metaText": "Master Duel Meta Top Decks Meta Weekly Kewl Tune The Fallen & The Virtuous",
      "sourceRank": 0,
      "ageDays": 1
    },
    {
      "id": "md-meta:/meta-weekly/230/kewl-tune/léon-cord/KoeJT/",
      "title": "Kewl Tune",
      "url": "https://www.masterduelmeta.com/meta-weekly/230/kewl-tune/léon-cord/KoeJT/",
      "source": "Master Duel Meta Top Decks",
      "format": "md",
      "creator": "Léon cord",
      "tournament": "Meta Weekly",
      "placement": "Top 4",
      "date": "2026-06-22T01:56:34.531Z",
      "views": 0,
      "rating": 17,
      "engines": [
        "The Fallen & The Virtuous"
      ],
      "notes": "",
      "archetypes": [
        "Kewl Tune",
        "The Fallen & The Virtuous"
      ],
      "mainIds": [
        97268402,
        97268402,
        97268402,
        94145021,
        17209452,
        17209452,
        17209452,
        23434538,
        43904702,
        16509007,
        16509007,
        16509007,
        59438930,
        14558127,
        14558127,
        14558127,
        73642296,
        73642296,
        52038441,
        16387555,
        16387555,
        16387555,
        89392810,
        89392810,
        89392810,
        42141493,
        42141493,
        42141493,
        99243014,
        97474300,
        14442329,
        24224830,
        78058681,
        78058681,
        78058681,
        30271097,
        30271097,
        30271097,
        10045474,
        10045474,
        10045474
      ],
      "extraIds": [
        87746184,
        42781164,
        42781164,
        42781164,
        39576656,
        15665977,
        15665977,
        88170262,
        88170262,
        41069676,
        4891376,
        78397661,
        22850702,
        65961304,
        93039339
      ],
      "sideIds": [],
      "metaText": "Master Duel Meta Top Decks Meta Weekly Kewl Tune The Fallen & The Virtuous",
      "sourceRank": 0,
      "ageDays": 1
    },
    {
      "id": "md-meta:/meta-weekly/230/kewl-tune/xhead695/GF6NO/",
      "title": "Kewl Tune",
      "url": "https://www.masterduelmeta.com/meta-weekly/230/kewl-tune/xhead695/GF6NO/",
      "source": "Master Duel Meta Top Decks",
      "format": "md",
      "creator": "Xhead695",
      "tournament": "Meta Weekly",
      "placement": "Top 16",
      "date": "2026-06-22T01:56:24.858Z",
      "views": 0,
      "rating": 17,
      "engines": [
        "The Fallen & The Virtuous"
      ],
      "notes": "",
      "archetypes": [
        "Kewl Tune",
        "The Fallen & The Virtuous"
      ],
      "mainIds": [
        97268402,
        97268402,
        97268402,
        94145021,
        94145021,
        17209452,
        17209452,
        17209452,
        23434538,
        43904702,
        16509007,
        16509007,
        16509007,
        59438930,
        59438930,
        14558127,
        14558127,
        14558127,
        73642296,
        73642296,
        73642296,
        16387555,
        16387555,
        16387555,
        89392810,
        89392810,
        89392810,
        42141493,
        42141493,
        99243014,
        97474300,
        97474300,
        14442329,
        24224830,
        78058681,
        78058681,
        78058681,
        30271097,
        30271097,
        10045474,
        10045474
      ],
      "extraIds": [
        87746184,
        42781164,
        42781164,
        39576656,
        15665977,
        15665977,
        88170262,
        88170262,
        41069676,
        68431965,
        4891376,
        78397661,
        22850702,
        65961304,
        65961304
      ],
      "sideIds": [],
      "metaText": "Master Duel Meta Top Decks Meta Weekly Kewl Tune The Fallen & The Virtuous",
      "sourceRank": 0,
      "ageDays": 1
    },
    {
      "id": "md-meta:/wcs-2026-qualifiers-dlv.-max/june-2026/mitsurugi/aymanmarwan/eZa9q/",
      "title": "Mitsurugi",
      "url": "https://www.masterduelmeta.com/wcs-2026-qualifiers-dlv.-max/june-2026/mitsurugi/aymanmarwan/eZa9q/",
      "source": "Master Duel Meta Top Decks",
      "format": "md",
      "creator": "Aymanmarwan",
      "tournament": "WCS 2026 DLv. Max",
      "placement": "",
      "date": "2026-06-21T23:58:19.892Z",
      "views": 0,
      "rating": 0,
      "engines": [
        "Pre-Preparation",
        "Fallen of the White Dragon",
        "The Fallen & The Virtuous"
      ],
      "notes": "",
      "archetypes": [
        "Mitsurugi",
        "Pre-Preparation",
        "Fallen of the White Dragon",
        "The Fallen & The Virtuous"
      ],
      "mainIds": [
        23434538,
        14558127,
        14558127,
        14558127,
        73642296,
        73642296,
        82782870,
        18176525,
        68468459,
        55273560,
        82489470,
        42141493,
        42141493,
        42141493,
        40543231,
        40543231,
        73819701,
        73819701,
        91800273,
        33854624,
        76948970,
        27204311,
        19899073,
        19899073,
        55397172,
        13332685,
        13332685,
        13048472,
        13048472,
        13048472,
        81560239,
        81560239,
        49721684,
        45171524,
        24224830,
        30271097,
        30271097,
        30271097,
        17954937,
        10045474,
        10045474,
        10045474
      ],
      "extraIds": [
        87746184,
        44146295,
        51409648,
        76666602,
        74586817,
        78397661,
        22850702,
        37926346,
        11398059,
        46772449,
        66011101,
        32530043,
        73898890,
        65741786,
        29301450
      ],
      "sideIds": [],
      "metaText": "Master Duel Meta Top Decks WCS 2026 DLv. Max Mitsurugi Pre-Preparation Fallen of the White Dragon The Fallen & The Virtuous",
      "sourceRank": 0,
      "ageDays": 1
    },
    {
      "id": "md-meta:/wcs-regional-qualifiers-win-streaks/june-2026/mitsurugi/yuki_toki/u40ty/",
      "title": "Mitsurugi",
      "url": "https://www.masterduelmeta.com/wcs-regional-qualifiers-win-streaks/june-2026/mitsurugi/yuki_toki/u40ty/",
      "source": "Master Duel Meta Top Decks",
      "format": "md",
      "creator": "yuki_toki",
      "tournament": "WCS Regional Qualifiers Win Streaks",
      "placement": "",
      "date": "2026-06-21T23:57:50.571Z",
      "views": 0,
      "rating": 0,
      "engines": [
        "Branded",
        "Pre-Preparation",
        "Fallen of the White Dragon",
        "The Fallen & The Virtuous"
      ],
      "notes": "",
      "archetypes": [
        "Mitsurugi",
        "Branded",
        "Pre-Preparation",
        "Fallen of the White Dragon",
        "The Fallen & The Virtuous"
      ],
      "mainIds": [
        23434538,
        14558127,
        14558127,
        14558127,
        82782870,
        18176525,
        68468459,
        55273560,
        60303688,
        42141493,
        42141493,
        42141493,
        40543231,
        40543231,
        73819701,
        73819701,
        19899073,
        19899073,
        55397172,
        13332685,
        13332685,
        13048472,
        13048472,
        13048472,
        44362883,
        81560239,
        81560239,
        81560239,
        49721684,
        49721684,
        45171524,
        76725398,
        24224830,
        30271097,
        30271097,
        30271097,
        17954937,
        10045474,
        40366667,
        40366667,
        40366667,
        16693934
      ],
      "extraIds": [
        41373230,
        87746184,
        44146295,
        51409648,
        76666602,
        78397661,
        11398059,
        46772449,
        6983839,
        66011101,
        93039339,
        65741786,
        65741786,
        70369116,
        29301450
      ],
      "sideIds": [],
      "metaText": "Master Duel Meta Top Decks WCS Regional Qualifiers Win Streaks Mitsurugi Branded Pre-Preparation Fallen of the White Dragon The Fallen & The Virtuous",
      "sourceRank": 0,
      "ageDays": 1
    },
    {
      "id": "md-meta:/meta-weekly/230/radiant-typhoon/parialife/bAE9Q/",
      "title": "Radiant Typhoon",
      "url": "https://www.masterduelmeta.com/meta-weekly/230/radiant-typhoon/parialife/bAE9Q/",
      "source": "Master Duel Meta Top Decks",
      "format": "md",
      "creator": "parialife",
      "tournament": "Meta Weekly",
      "placement": "Top 16",
      "date": "2026-06-22T01:56:15.005Z",
      "views": 0,
      "rating": 6,
      "engines": [
        "Shiina",
        "The Fallen & The Virtuous"
      ],
      "notes": "",
      "archetypes": [
        "Radiant Typhoon",
        "Shiina",
        "The Fallen & The Virtuous"
      ],
      "mainIds": [
        23434538,
        54143349,
        54143349,
        54143349,
        27755794,
        80538047,
        80538047,
        80538047,
        34242278,
        16922142,
        16922142,
        16922142,
        85315450,
        53927851,
        12197223,
        12197223,
        12197223,
        25311006,
        5318639,
        5318639,
        5318639,
        48130397,
        48130397,
        48130397,
        24224830,
        24299458,
        24299458,
        24299458,
        25940932,
        67115133,
        67115133,
        67115133,
        94103142,
        20508881,
        20508881,
        20508881,
        30271097,
        30271097,
        30271097,
        53813120
      ],
      "extraIds": [
        54757758,
        11765832,
        46396218,
        87746184,
        89851827,
        76666602,
        85065943,
        78397661,
        71068247,
        71166481,
        95113856,
        30674956,
        39341885,
        39341885,
        49105782
      ],
      "sideIds": [],
      "metaText": "Master Duel Meta Top Decks Meta Weekly Radiant Typhoon Shiina The Fallen & The Virtuous",
      "sourceRank": 0,
      "ageDays": 1
    },
    {
      "id": "md-meta:/wcs-2026-qualifiers-dlv.-max/june-2026/radiant-typhoon-zoodiac/mateja/rQqId/",
      "title": "Radiant Typhoon Zoodiac",
      "url": "https://www.masterduelmeta.com/wcs-2026-qualifiers-dlv.-max/june-2026/radiant-typhoon-zoodiac/mateja/rQqId/",
      "source": "Master Duel Meta Top Decks",
      "format": "md",
      "creator": "mateja",
      "tournament": "WCS 2026 DLv. Max",
      "placement": "",
      "date": "2026-06-21T23:58:13.171Z",
      "views": 0,
      "rating": 3,
      "engines": [
        "Radiant Typhoon Vision",
        "The Fallen & The Virtuous"
      ],
      "notes": "",
      "archetypes": [
        "Radiant Typhoon Zoodiac",
        "Radiant Typhoon Vision",
        "The Fallen & The Virtuous"
      ],
      "mainIds": [
        94145021,
        94145021,
        23434538,
        14558127,
        14558127,
        14558127,
        54143349,
        54143349,
        54143349,
        27755794,
        80538047,
        80538047,
        80538047,
        78872731,
        78872731,
        78872731,
        42141493,
        42141493,
        42141493,
        16922142,
        16922142,
        16922142,
        85315450,
        53927851,
        5318639,
        5318639,
        5318639,
        24224830,
        25940932,
        25940932,
        67115133,
        67115133,
        67115133,
        20508881,
        20508881,
        20508881,
        30271097,
        30271097,
        30271097,
        53813120
      ],
      "extraIds": [
        87746184,
        78397661,
        65305468,
        26973555,
        4423206,
        71068247,
        74393852,
        85115440,
        48905153,
        11510448,
        90448279,
        90512490,
        39341885,
        39341885,
        49105782
      ],
      "sideIds": [],
      "metaText": "Master Duel Meta Top Decks WCS 2026 DLv. Max Radiant Typhoon Zoodiac Radiant Typhoon Vision The Fallen & The Virtuous",
      "sourceRank": 0,
      "ageDays": 1
    },
    {
      "id": "md-meta:/wcs-2026-qualifiers-dlv.-max/june-2026/regenesis/tom-sutter/RC6AA/",
      "title": "Regenesis",
      "url": "https://www.masterduelmeta.com/wcs-2026-qualifiers-dlv.-max/june-2026/regenesis/tom-sutter/RC6AA/",
      "source": "Master Duel Meta Top Decks",
      "format": "md",
      "creator": "Tom Sutter",
      "tournament": "WCS 2026 DLv. Max",
      "placement": "",
      "date": "2026-06-22T02:31:52.463Z",
      "views": 0,
      "rating": 0,
      "engines": [
        "Dogmatika",
        "Fallen of the White Dragon",
        "The Fallen & The Virtuous"
      ],
      "notes": "",
      "archetypes": [
        "Regenesis",
        "Dogmatika",
        "Fallen of the White Dragon",
        "The Fallen & The Virtuous"
      ],
      "mainIds": [
        94145021,
        94145021,
        23434538,
        60303688,
        68468459,
        55273560,
        73819701,
        6637331,
        33854624,
        72656408,
        22938501,
        96540807,
        96540807,
        102380,
        102380,
        102380,
        69680031,
        95718355,
        95718355,
        95718355,
        59323650,
        73355772,
        73355772,
        22812963,
        47082621,
        31786838,
        31786838,
        31786838,
        1984618,
        1984618,
        1984618,
        67171933,
        67171933,
        67171933,
        30271097,
        30271097,
        30271097,
        82956214,
        82956214,
        27781371
      ],
      "extraIds": [
        80532587,
        11765832,
        41373230,
        87746184,
        87746184,
        3410461,
        44146295,
        24915933,
        76666602,
        93125329,
        78397661,
        53971455,
        9940036,
        93039339,
        10019086
      ],
      "sideIds": [],
      "metaText": "Master Duel Meta Top Decks WCS 2026 DLv. Max Regenesis Dogmatika Fallen of the White Dragon The Fallen & The Virtuous",
      "sourceRank": 0,
      "ageDays": 1
    },
    {
      "id": "md-meta:/master-i/june-2026/sky-striker/cnydo/VfmZW/",
      "title": "Sky Striker",
      "url": "https://www.masterduelmeta.com/master-i/june-2026/sky-striker/cnydo/VfmZW/",
      "source": "Master Duel Meta Top Decks",
      "format": "md",
      "creator": "cnydo",
      "tournament": "Master I",
      "placement": "",
      "date": "2026-06-21T23:57:04.416Z",
      "views": 0,
      "rating": 5,
      "engines": [
        "The Fallen & The Virtuous"
      ],
      "notes": "",
      "archetypes": [
        "Sky Striker",
        "The Fallen & The Virtuous"
      ],
      "mainIds": [
        20357457,
        23434538,
        26077387,
        26077387,
        26077387,
        37351133,
        70368879,
        70368879,
        70368879,
        99550630,
        25955749,
        63166095,
        63166095,
        63166095,
        21623008,
        25311006,
        32807846,
        35269904,
        34433770,
        34433770,
        5318639,
        52340444,
        51227866,
        98338152,
        98338152,
        98338152,
        24299458,
        24299458,
        24299458,
        9726840,
        9726840,
        9726840,
        24224830,
        20508881,
        20508881,
        20508881,
        30271097,
        30271097,
        30271097,
        49299410
      ],
      "extraIds": [
        87746184,
        78397661,
        93039339,
        76072561,
        76072561,
        8491308,
        63288573,
        63288573,
        63288573,
        90673288,
        25072579,
        75147529,
        98462037,
        17217034,
        63013339
      ],
      "sideIds": [],
      "metaText": "Master Duel Meta Top Decks Master I Sky Striker The Fallen & The Virtuous",
      "sourceRank": 0,
      "ageDays": 1
    },
    {
      "id": "md-meta:/master-i/june-2026/sky-striker/bo-bae/SnQTF/",
      "title": "Sky Striker",
      "url": "https://www.masterduelmeta.com/master-i/june-2026/sky-striker/bo-bae/SnQTF/",
      "source": "Master Duel Meta Top Decks",
      "format": "md",
      "creator": "Bo-Bae",
      "tournament": "Master I",
      "placement": "",
      "date": "2026-06-21T22:12:14.458Z",
      "views": 0,
      "rating": 5,
      "engines": [
        "The Fallen & The Virtuous"
      ],
      "notes": "",
      "archetypes": [
        "Sky Striker",
        "The Fallen & The Virtuous"
      ],
      "mainIds": [
        23434538,
        14558127,
        14558127,
        14558127,
        26077387,
        26077387,
        26077387,
        37351133,
        37351133,
        70368879,
        70368879,
        70368879,
        32807846,
        35261759,
        35261759,
        35261759,
        25311006,
        25311006,
        63166095,
        63166095,
        63166095,
        34433770,
        34433770,
        24224830,
        52340444,
        98338152,
        98338152,
        98338152,
        24299458,
        24299458,
        24299458,
        9726840,
        9726840,
        9726840,
        20508881,
        20508881,
        20508881,
        30271097,
        30271097,
        30271097
      ],
      "extraIds": [
        87746184,
        78397661,
        93039339,
        76072561,
        76072561,
        76072561,
        63288573,
        63288573,
        63288573,
        90673288,
        8491308,
        25072579,
        75147529,
        98462037,
        17217034
      ],
      "sideIds": [],
      "metaText": "Master Duel Meta Top Decks Master I Sky Striker The Fallen & The Virtuous",
      "sourceRank": 0,
      "ageDays": 1
    },
    {
      "id": "md-meta:/wcs-2026-qualifiers-dlv.-max/june-2026/traptrix/aumez/iV2Cj/",
      "title": "Traptrix",
      "url": "https://www.masterduelmeta.com/wcs-2026-qualifiers-dlv.-max/june-2026/traptrix/aumez/iV2Cj/",
      "source": "Master Duel Meta Top Decks",
      "format": "md",
      "creator": "Aumez",
      "tournament": "WCS 2026 DLv. Max",
      "placement": "",
      "date": "2026-06-22T02:31:45.751Z",
      "views": 0,
      "rating": 0,
      "engines": [
        "Therion",
        "Brilliant Fusion",
        "Naturia Beast Glow-Up Bulb",
        "The Fallen & The Virtuous"
      ],
      "notes": "",
      "archetypes": [
        "Traptrix",
        "Therion",
        "Brilliant Fusion",
        "Naturia Beast Glow-Up Bulb",
        "The Fallen & The Virtuous"
      ],
      "mainIds": [
        67441435,
        23434538,
        14558127,
        14558127,
        14558127,
        73642296,
        73642296,
        51831560,
        51831560,
        91812341,
        91812341,
        91812341,
        45803070,
        82738277,
        82738277,
        28868394,
        49964567,
        35622739,
        132308,
        132308,
        75416738,
        49027020,
        49027020,
        67972302,
        67972302,
        67972302,
        42141493,
        42141493,
        42141493,
        10604644,
        83610035,
        13903402,
        81439173,
        84792926,
        12801833,
        75493362,
        75493362,
        75493362,
        7394770,
        7394770,
        7394770,
        24224830,
        24299458,
        24299458,
        24299458,
        30271097,
        30271097,
        30271097,
        29616929,
        69599136,
        15693423,
        15693423,
        15693423,
        10045474,
        10045474,
        10045474,
        31548215,
        74577599,
        74577599,
        89824842
      ],
      "extraIds": [
        3113836,
        87746184,
        33198837,
        78397661,
        6511113,
        3828844,
        1688285,
        9349094,
        93039339,
        73639099,
        73639099,
        21200905,
        952523,
        952523,
        29301450
      ],
      "sideIds": [],
      "metaText": "Master Duel Meta Top Decks WCS 2026 DLv. Max Traptrix Therion Brilliant Fusion Naturia Beast Glow-Up Bulb The Fallen & The Virtuous",
      "sourceRank": 0,
      "ageDays": 1
    },
    {
      "id": "md-meta:/wcs-2026-qualifiers-dlv.-max/june-2026/tri-brigade/willyofruit/ebK8W/",
      "title": "Tri-Brigade",
      "url": "https://www.masterduelmeta.com/wcs-2026-qualifiers-dlv.-max/june-2026/tri-brigade/willyofruit/ebK8W/",
      "source": "Master Duel Meta Top Decks",
      "format": "md",
      "creator": "willyofruit",
      "tournament": "WCS 2026 DLv. Max",
      "placement": "",
      "date": "2026-06-21T19:45:00.000Z",
      "views": 0,
      "rating": 0,
      "engines": [
        "Yummy",
        "The Fallen & The Virtuous"
      ],
      "notes": "",
      "archetypes": [
        "Tri-Brigade",
        "Yummy",
        "The Fallen & The Virtuous"
      ],
      "mainIds": [
        24508238,
        14816857,
        14816857,
        14816857,
        68810435,
        68810435,
        31425736,
        4215180,
        10966439,
        10966439,
        50810455,
        56196385,
        14558127,
        14558127,
        73642296,
        73642296,
        73642296,
        19304410,
        87209160,
        87209160,
        87209160,
        42141493,
        84192580,
        84192580,
        25311006,
        25311006,
        93360904,
        66975205,
        57103969,
        57103969,
        24299458,
        24299458,
        24224830,
        10793085,
        10793085,
        29369059,
        30271097,
        30271097,
        92269002,
        92269002,
        10045474,
        10045474,
        10045474,
        86379342,
        40975243
      ],
      "extraIds": [
        87746184,
        76666602,
        67098897,
        31603289,
        93192592,
        78397661,
        30581601,
        10019086,
        41999284,
        26847978,
        47163170,
        29301450,
        33781156,
        52331012,
        99726621
      ],
      "sideIds": [],
      "metaText": "Master Duel Meta Top Decks WCS 2026 DLv. Max Tri-Brigade Yummy The Fallen & The Virtuous",
      "sourceRank": 0,
      "ageDays": 1
    },
    {
      "id": "md-meta:/meta-weekly/230/vanquish-soul-k9/awsiel/Kawnj/",
      "title": "Vanquish Soul K9",
      "url": "https://www.masterduelmeta.com/meta-weekly/230/vanquish-soul-k9/awsiel/Kawnj/",
      "source": "Master Duel Meta Top Decks",
      "format": "md",
      "creator": "Awsiel",
      "tournament": "Meta Weekly",
      "placement": "Top 16",
      "date": "2026-06-22T01:56:21.532Z",
      "views": 0,
      "rating": 3.5,
      "engines": [
        "K9",
        "The Fallen & The Virtuous"
      ],
      "notes": "",
      "archetypes": [
        "Vanquish Soul K9",
        "K9",
        "The Fallen & The Virtuous"
      ],
      "mainIds": [
        23434538,
        14558127,
        14558127,
        14558127,
        29280200,
        29280200,
        29280200,
        29302858,
        29302858,
        9091064,
        9091064,
        47960073,
        47960073,
        92248362,
        92248362,
        92248362,
        28642461,
        28642461,
        55031170,
        91025875,
        93156774,
        93156774,
        93156774,
        91800273,
        92895501,
        92895501,
        91073013,
        32807846,
        54562327,
        35550352,
        80181649,
        80181649,
        48130397,
        48130397,
        48130397,
        53792930,
        30271097,
        30271097,
        30271097,
        60883493
      ],
      "extraIds": [
        54757758,
        96334243,
        11765832,
        87746184,
        44146295,
        78397661,
        27420823,
        67515699,
        40673853,
        90303227,
        90448279,
        28168628,
        28168628,
        29301450,
        74997493
      ],
      "sideIds": [],
      "metaText": "Master Duel Meta Top Decks Meta Weekly Vanquish Soul K9 K9 The Fallen & The Virtuous",
      "sourceRank": 0,
      "ageDays": 1
    }
  ]
}